{"url":"http://www.rtve.es/alacarta/videos/telediario/telediario-15-horas-27-09-14/2779908/","subtitles":[{"ns":"seg_11","text":"con el que convoca"},{"ns":"seg_13","text":"para el próximo 9 de noviembre."},{"ns":"seg_16","text":"en el Palau de la Generalitat,"},{"ns":"seg_19","text":"y en presencia de todos los partidos"},{"ns":"seg_22","text":"excepto Iniciativa."},{"ns":"seg_25","text":"con un marco legal para la votación."},{"ns":"seg_32","text":"quiere ser escuchada, quiere votar,"},{"ns":"seg_37","text":"de 7 millones de personas,"},{"ns":"seg_40","text":"muchas ellas de tierras españolas."},{"ns":"seg_48","text":"y consideramos que es un error"},{"ns":"seg_52","text":"de la Generalitat."},{"ns":"seg_56","text":"divide a los catalanes,"},{"ns":"seg_60","text":"y del sentir de los tiempos."},{"ns":"seg_66","text":"el procedimiento"},{"ns":"seg_68","text":"ante el Tribunal Constitucional."},{"ns":"seg_71","text":""},{"ns":"seg_72","text":"de Estado elaborará,"},{"ns":"seg_74","text":"un informe a partir"},{"ns":"seg_77","text":"los dos recursos:"},{"ns":"seg_79","text":""},{"ns":"seg_81","text":"firmado hoy."},{"ns":"seg_84","text":"se reunirá el próximo lunes."},{"ns":"seg_89","text":""},{"ns":"seg_90","text":"en el Palacio de la Moncloa,"},{"ns":"seg_92","text":""},{"ns":"seg_94","text":""},{"ns":"seg_95","text":"vuelve en estos momentos a España"},{"ns":"seg_97","text":""},{"ns":"seg_98","text":"a la Gran Muralla"},{"ns":"seg_100","text":"con los periodistas,"},{"ns":"seg_102","text":""},{"ns":"seg_104","text":"en un lío\"."},{"ns":"seg_109","text":""},{"ns":"seg_111","text":"políticas."},{"ns":"seg_117","text":"votar"},{"ns":"seg_118","text":"voten."},{"ns":"seg_121","text":""},{"ns":"seg_122","text":"el decreto se va a impugnar,"},{"ns":"seg_127","text":"que la consulta no se va a realizar"},{"ns":"seg_132","text":"es una enorme fractura y frustración"},{"ns":"seg_135","text":"y en la sociedad española."},{"ns":"seg_139","text":"en tela de juicio"},{"ns":"seg_141","text":""},{"ns":"seg_143","text":"la democracias"},{"ns":"seg_145","text":"estados"},{"ns":"seg_148","text":"totalitarios."},{"ns":"seg_153","text":"su ofensiva en Irak."},{"ns":"seg_156","text":"han salido esta mañana"},{"ns":"seg_160","text":"han salido esta mañana"},{"ns":"seg_162","text":"para atacar objetivos yihadistas."},{"ns":"seg_165","text":"de que el Parlamento Británico"},{"ns":"seg_168","text":"en la lucha contra el yihadismo."},{"ns":"seg_171","text":"se unen a las de Estados Unidos,"},{"ns":"seg_174","text":""},{"ns":"seg_177","text":"y anuncia que sus tropas"},{"ns":"seg_180","text":"contra los yihadistas."},{"ns":"seg_185","text":"pederasta de Ciudad Lineal,"},{"ns":"seg_187","text":"en prisión."},{"ns":"seg_189","text":""},{"ns":"seg_191","text":"de aislamiento,"},{"ns":"seg_193","text":"para evitar posibles agresiones."},{"ns":"seg_196","text":""},{"ns":"seg_199","text":"sexuales y dos homicidios"},{"ns":"seg_202","text":""},{"ns":"seg_206","text":"Manuel García Viejo"},{"ns":"seg_207","text":"de San Isidro, en Madrid."},{"ns":"seg_211","text":""},{"ns":"seg_212","text":"esta mañana."},{"ns":"seg_214","text":"es el segundo español"},{"ns":"seg_216","text":""},{"ns":"seg_218","text":"de la Salud,"},{"ns":"seg_220","text":"han muerto por el virus."},{"ns":"seg_228","text":"del mismo equipo que \"Intocable\","},{"ns":"seg_230","text":"de San Sebastián."},{"ns":"seg_233","text":"Benicio del Toro"},{"ns":"seg_240","text":"Benicio del Toro"},{"ns":"seg_241","text":"a toda su carrera."},{"ns":"seg_245","text":"en el que la Liga de fútbol"},{"ns":"seg_248","text":""},{"ns":"seg_258","text":"de la liga de campeones juegan hoy"},{"ns":"seg_261","text":"en 21 dias para Madrid, Atlético,"},{"ns":"seg_264","text":""},{"ns":"seg_266","text":"con Gareth Bale"},{"ns":"seg_269","text":"donde debutó hace un año."},{"ns":"seg_271","text":"en el Camp Nou sin Piqué niAlba"},{"ns":"seg_275","text":""},{"ns":"seg_276","text":"el Atlético-Sevilla"},{"ns":"seg_278","text":"otra vez en el banquillo."},{"ns":"seg_280","text":""},{"ns":"seg_282","text":"contra Eibar."},{"ns":"seg_287","text":"para que Real Madrid y Barcelona"},{"ns":"seg_289","text":""},{"ns":"seg_291","text":""},{"ns":"seg_293","text":"Madrid-Barça."},{"ns":"seg_295","text":""},{"ns":"seg_297","text":"de Vitoria."},{"ns":"seg_311","text":"de las diez y media de la mañana"},{"ns":"seg_314","text":"el decreto de convocatoria"},{"ns":"seg_316","text":"del 9 de noviembre."},{"ns":"seg_319","text":"en el Palau de la Generalitat"},{"ns":"seg_327","text":"en el Palau de la Generalitat"},{"ns":"seg_330","text":"de todo el Gobierno catalán,"},{"ns":"seg_332","text":"y representantes de los partidos"},{"ns":"seg_335","text":"excepto Iniciativa."},{"ns":"seg_347","text":"simbolismo"},{"ns":"seg_358","text":"y la pluma con la que se ha firmado."},{"ns":"seg_373","text":"Esquerra ni de iniciativa."},{"ns":"seg_382","text":"para inmortalizar el momento,"},{"ns":"seg_388","text":"un antes y un después"},{"ns":"seg_393","text":""},{"ns":"seg_398","text":"llegado hasta aquí"},{"ns":"seg_403","text":"guiado el proceso."},{"ns":"seg_408","text":"la consulta,"},{"ns":"seg_409","text":"la trascendencia del momento."},{"ns":"seg_412","text":"al Gobierno."},{"ns":"seg_414","text":"a pactar las condiciones"},{"ns":"seg_426","text":"que no anule la convocatoria."},{"ns":"seg_429","text":""},{"ns":"seg_430","text":"de los ciudadanos."},{"ns":"seg_433","text":"es la de siete millones y medio"},{"ns":"seg_435","text":"de orígenes muy diversos,"},{"ns":"seg_439","text":"de tierras españolas."},{"ns":"seg_442","text":"su mensaje al resto de Europa."},{"ns":"seg_445","text":"decía Mas, antes de insistir"},{"ns":"seg_450","text":"decía Mas, antes de insistir"},{"ns":"seg_452","text":"se resuelven con política."},{"ns":"seg_455","text":"a la Plaza de Sant Jaume,"},{"ns":"seg_457","text":"centenares de personas."},{"ns":"seg_459","text":""},{"ns":"seg_461","text":"de convocatoria"},{"ns":"seg_463","text":"de firmarlo, la Ley de Consultas."},{"ns":"seg_470","text":"el decreto de convocatoria,"},{"ns":"seg_472","text":"un portal en Internet"},{"ns":"seg_475","text":""},{"ns":"seg_477","text":"podría votar, cómo hacerlo y dónde."},{"ns":"seg_481","text":"descargarse las papeletas"},{"ns":"seg_483","text":""},{"ns":"seg_487","text":"convocara la consulta,"},{"ns":"seg_489","text":"Sáenz de Santamaría"},{"ns":"seg_491","text":"de La Moncloa."},{"ns":"seg_493","text":"en que el referéndum"},{"ns":"seg_495","text":""},{"ns":"seg_496","text":""},{"ns":"seg_503","text":"encima de la ley"},{"ns":"seg_510","text":"ha dicho la vicepresidenta."},{"ns":"seg_514","text":"responsabilidad del gobierno velar"},{"ns":"seg_519","text":"gobierno seguirá trabajando"},{"ns":"seg_524","text":"España y Cataluña"},{"ns":"seg_530","text":"su primer paso"},{"ns":"seg_543","text":"consideramos que es un error"},{"ns":"seg_550","text":"Generalitat."},{"ns":"seg_553","text":"divide a los catalanes,"},{"ns":"seg_557","text":"los tiempos."},{"ns":"seg_567","text":"la voluntad soberana"},{"ns":"seg_572","text":""},{"ns":"seg_574","text":"transigir"},{"ns":"seg_577","text":""},{"ns":"seg_578","text":"conjunto de los españoles."},{"ns":"seg_579","text":"el referéndum es inconstitucional"},{"ns":"seg_581","text":"no permitirá que se celebre."},{"ns":"seg_586","text":"también ha anunciado"},{"ns":"seg_587","text":"el Gobierno ha iniciado los trámites"},{"ns":"seg_589","text":"tanto la Ley de Consultas"},{"ns":"seg_592","text":""},{"ns":"seg_594","text":""},{"ns":"seg_603","text":"mañana a través del ministro de"},{"ns":"seg_608","text":""},{"ns":"seg_609","text":"solicitado un informe"},{"ns":"seg_614","text":"periodo de 48 horas"},{"ns":"seg_619","text":"documento encima de la mesa."},{"ns":"seg_627","text":"extraordinario"},{"ns":"seg_632","text":"de consultas"},{"ns":"seg_638","text":""},{"ns":"seg_643","text":"presidente del alto tribunal"},{"ns":"seg_648","text":"asunto."},{"ns":"seg_649","text":"y produce el efecto"},{"ns":"seg_651","text":"ningún efecto."},{"ns":"seg_653","text":""},{"ns":"seg_658","text":"el presidente del Gobierno"},{"ns":"seg_660","text":""},{"ns":"seg_662","text":"con periodistas,"},{"ns":"seg_664","text":"textualmente, que Artur Mas"},{"ns":"seg_666","text":""},{"ns":"seg_680","text":"España."},{"ns":"seg_684","text":"muralla China."},{"ns":"seg_688","text":"que Artur más se ha metido en un lío"},{"ns":"seg_693","text":""},{"ns":"seg_697","text":"primer viaje oficial a China"},{"ns":"seg_702","text":"relaciones comerciales"},{"ns":"seg_708","text":"han comparecido esta mañana"},{"ns":"seg_710","text":""},{"ns":"seg_711","text":"se felicitan"},{"ns":"seg_713","text":"mientras que PSC y PP"},{"ns":"seg_715","text":"el referéndum."},{"ns":"seg_728","text":"ahora la reacción del gobierno."},{"ns":"seg_736","text":"suspensión cautelar"},{"ns":"seg_740","text":""},{"ns":"seg_745","text":"preparativos."},{"ns":"seg_753","text":"de todo."},{"ns":"seg_759","text":""},{"ns":"seg_771","text":"expectativas que generan"},{"ns":"seg_775","text":""},{"ns":"seg_781","text":"actitud del presidente catalán"},{"ns":"seg_785","text":""},{"ns":"seg_790","text":"político temerario."},{"ns":"seg_797","text":"carrera política de Artur más."},{"ns":"seg_800","text":"los distintos partidos"},{"ns":"seg_802","text":"la convocatoria de la consulta."},{"ns":"seg_804","text":"sabe que el decreto"},{"ns":"seg_806","text":"que el decreto se va a paralizar,"},{"ns":"seg_808","text":""},{"ns":"seg_811","text":"es una enorme fractura y frustración"},{"ns":"seg_814","text":"y en la sociedad española."},{"ns":"seg_817","text":"no haga el ridículo"},{"ns":"seg_819","text":"en el espejo escocés,"},{"ns":"seg_825","text":"con una prohibición,"},{"ns":"seg_827","text":""},{"ns":"seg_829","text":"constitucionalistas,"},{"ns":"seg_831","text":"el Estado de derecho estemos unidos."},{"ns":"seg_841","text":"es poner en tela de juicio"},{"ns":"seg_844","text":"y poner en tela de juicio"},{"ns":"seg_846","text":""},{"ns":"seg_847","text":"es de los Estados"},{"ns":"seg_850","text":"y de los modelos totalitarios;"},{"ns":"seg_854","text":"por encima de la ley,"},{"ns":"seg_856","text":"de hacer el señor Mas."},{"ns":"seg_859","text":"de la comparecencia de Jordi Pujol"},{"ns":"seg_861","text":"hoy los partidos catalanes"},{"ns":"seg_863","text":"las explicaciones del expresident."},{"ns":"seg_870","text":"a Jordi Pujol"},{"ns":"seg_872","text":"convencidos"},{"ns":"seg_874","text":"a las preguntas"},{"ns":"seg_877","text":"oculta en paraísos fiscales."},{"ns":"seg_880","text":"se respondieron a muchas."},{"ns":"seg_885","text":"de las preguntas que formularon"},{"ns":"seg_888","text":""},{"ns":"seg_889","text":"de la oposición estan de acuerdo"},{"ns":"seg_893","text":""},{"ns":"seg_896","text":"sin responder."},{"ns":"seg_898","text":""},{"ns":"seg_900","text":"como seamos capaces"},{"ns":"seg_903","text":"y de nuestra capacidad"},{"ns":"seg_907","text":"sobre esta cuestión."},{"ns":"seg_910","text":"una escena teatral de enfado"},{"ns":"seg_914","text":"esconder la realidad."},{"ns":"seg_918","text":"o no está en condiciones"},{"ns":"seg_921","text":"que los diputados le formulaban."},{"ns":"seg_925","text":"con esa comparecencia"},{"ns":"seg_927","text":"en el Caso CiU."},{"ns":"seg_930","text":"hace mucho tiempo"},{"ns":"seg_932","text":""},{"ns":"seg_935","text":"de Investigación"},{"ns":"seg_937","text":""},{"ns":"seg_939","text":"votará el miercoles"},{"ns":"seg_941","text":"esa comisión de investigación."},{"ns":"seg_944","text":"a excepción de Convergencia i Unió."},{"ns":"seg_949","text":"de Ministros aprobara ayer"},{"ns":"seg_951","text":""},{"ns":"seg_953","text":"ha destacado que, por primera vez,"},{"ns":"seg_956","text":"de la deuda."},{"ns":"seg_958","text":"de Cospedal,"},{"ns":"seg_960","text":"a políticas sociales."},{"ns":"seg_965","text":"del Partido Popular"},{"ns":"seg_967","text":"es digno de confianza"},{"ns":"seg_969","text":"a que los ciudadanos"},{"ns":"seg_971","text":"de las medidas"},{"ns":"seg_973","text":""},{"ns":"seg_975","text":"ha garantizado"},{"ns":"seg_977","text":"que los presupuestos de 2015"},{"ns":"seg_981","text":"de la recuperación."},{"ns":"seg_984","text":"en los presupuestos,"},{"ns":"seg_987","text":"a pagar intereses de la deuda"},{"ns":"seg_990","text":"que la del año anterior,"},{"ns":"seg_993","text":"y eso es mucho dinero,"},{"ns":"seg_998","text":"a políticas sociales."},{"ns":"seg_1001","text":""},{"ns":"seg_1003","text":"para Europa y ahora, dice,"},{"ns":"seg_1005","text":""},{"ns":"seg_1007","text":"por encima de la media europea."},{"ns":"seg_1012","text":"los Presupuestos de 2015"},{"ns":"seg_1014","text":"y los recortes."},{"ns":"seg_1017","text":"que sólo sirven para consolidar"},{"ns":"seg_1019","text":"ha dicho, durante esta legislatura."},{"ns":"seg_1026","text":"que enmascaran un recorte"},{"ns":"seg_1028","text":"en sanidad,"},{"ns":"seg_1032","text":"y en servicios sociales."},{"ns":"seg_1035","text":"que tiene en estos momentos España,"},{"ns":"seg_1039","text":""},{"ns":"seg_1042","text":"en la Audiencia Nacional"},{"ns":"seg_1051","text":"para crear empleo."},{"ns":"seg_1054","text":"en la Audiencia Nacional"},{"ns":"seg_1056","text":"español detenido ayer en Melilla,"},{"ns":"seg_1059","text":"en la que también hubo"},{"ns":"seg_1061","text":""},{"ns":"seg_1063","text":"una célula terrorista"},{"ns":"seg_1065","text":""},{"ns":"seg_1066","text":"y, según el Ministerio del Interior,"},{"ns":"seg_1070","text":"especialista en armas"},{"ns":"seg_1072","text":"combatiendo con los yihadistas"},{"ns":"seg_1075","text":""},{"ns":"seg_1077","text":"el grupo se dedicaba a reclutar"},{"ns":"seg_1079","text":""},{"ns":"seg_1089","text":"británicos en iniciar"},{"ns":"seg_1092","text":"contra los yihadistas"},{"ns":"seg_1094","text":""},{"ns":"seg_1095","text":"en territorio iraquí"},{"ns":"seg_1098","text":"las posiciones de los extremistas."},{"ns":"seg_1102","text":"de que el parlamento británico"},{"ns":"seg_1105","text":""},{"ns":"seg_1106","text":""},{"ns":"seg_1108","text":"Bélgica, Holanda y Dinamarca."},{"ns":"seg_1111","text":"actúa en Siria."},{"ns":"seg_1116","text":"cambia de actitud."},{"ns":"seg_1118","text":"ha mostrado hoy, por primera vez,"},{"ns":"seg_1121","text":"a la coalición internacional"},{"ns":"seg_1123","text":""},{"ns":"seg_1125","text":"tras participar en Nueva York"},{"ns":"seg_1128","text":""},{"ns":"seg_1131","text":""},{"ns":"seg_1133","text":"en Siria,"},{"ns":"seg_1135","text":"para ello."},{"ns":"seg_1138","text":"se había mostrado reticiente"},{"ns":"seg_1140","text":"contra el Estado Islámico."},{"ns":"seg_1143","text":""},{"ns":"seg_1144","text":"con los terroristas"},{"ns":"seg_1146","text":""},{"ns":"seg_1148","text":"una operación terrestre,"},{"ns":"seg_1150","text":"a participar."},{"ns":"seg_1154","text":"ha dicho Erdogan."},{"ns":"seg_1156","text":"de exclusión aérea."},{"ns":"seg_1159","text":"de seguridad en territorio sirio,"},{"ns":"seg_1162","text":""},{"ns":"seg_1164","text":""},{"ns":"seg_1165","text":"que huyen de Siria,"},{"ns":"seg_1167","text":""},{"ns":"seg_1171","text":"cientos de kurdos de Turquía"},{"ns":"seg_1174","text":"para cruzar a Siria."},{"ns":"seg_1176","text":"a sus hermanos kurdos,"},{"ns":"seg_1181","text":"en la ciudad de Kobane,"},{"ns":"seg_1183","text":""},{"ns":"seg_1185","text":"de la coalición internacional,"},{"ns":"seg_1187","text":"esta mañana"},{"ns":"seg_1190","text":"en el norte de Siria,"},{"ns":"seg_1193","text":"de derechos humanos."},{"ns":"seg_1197","text":"ha reclamado en la ONU"},{"ns":"seg_1201","text":"ha reclamado en la ONU"},{"ns":"seg_1204","text":"del Estado palestino,"},{"ns":"seg_1206","text":""},{"ns":"seg_1207","text":"de los ataques militares en Gaza."},{"ns":"seg_1223","text":"presidente palestino"},{"ns":"seg_1226","text":""},{"ns":"seg_1234","text":"que Israel se retire de los"},{"ns":"seg_1238","text":""},{"ns":"seg_1240","text":"reconocido que está lejos"},{"ns":"seg_1244","text":"nuclear iraní."},{"ns":"seg_1248","text":"finalizado"},{"ns":"seg_1251","text":""},{"ns":"seg_1261","text":"Kong a unas 4000 personas"},{"ns":"seg_1265","text":"democráticas."},{"ns":"seg_1274","text":"del segundo volcán más alto"},{"ns":"seg_1276","text":"de senderistas"},{"ns":"seg_1278","text":"en la montaña."},{"ns":"seg_1280","text":""},{"ns":"seg_1282","text":"al Ejército para rescatarlos."},{"ns":"seg_1285","text":"a la población que se aleje"},{"ns":"seg_1287","text":"los tres kilómetros."},{"ns":"seg_1290","text":"ha forzado"},{"ns":"seg_1292","text":""},{"ns":"seg_1298","text":"en una operación"},{"ns":"seg_1299","text":"y la Policía Nacional"},{"ns":"seg_1301","text":""},{"ns":"seg_1303","text":"operaba en Alicante y Murcia,"},{"ns":"seg_1305","text":"para la elaboración de droga."},{"ns":"seg_1308","text":"de 38 kilos de cocaína,"},{"ns":"seg_1311","text":""},{"ns":"seg_1317","text":"de Ciudad Lineal, Antonio Ortiz,"},{"ns":"seg_1320","text":"en la cárcel."},{"ns":"seg_1322","text":"comunicada y sin fianza."},{"ns":"seg_1326","text":"madrileña de Soto del Real."},{"ns":"seg_1337","text":"hora."},{"ns":"seg_1349","text":"en un fichero de especial"},{"ns":"seg_1353","text":""},{"ns":"seg_1357","text":"para evitar agresiones."},{"ns":"seg_1372","text":"a una rueda de reconocimiento"},{"ns":"seg_1376","text":""},{"ns":"seg_1380","text":"y sobre todo los pederastas"},{"ns":"seg_1382","text":"muy denostados en las cárceles"},{"ns":"seg_1384","text":""},{"ns":"seg_1385","text":"comienza garantizando su seguridad."},{"ns":"seg_1404","text":"menos horas de patio"},{"ns":"seg_1405","text":""},{"ns":"seg_1407","text":"tratamiento psiquiátrico"},{"ns":"seg_1410","text":"de internos."},{"ns":"seg_1421","text":"los testículos."},{"ns":"seg_1427","text":"una disminución de la impulsividad"},{"ns":"seg_1434","text":"suficiente."},{"ns":"seg_1436","text":"su consentimiento para recibir"},{"ns":"seg_1439","text":"y en ocasiones esto puede conllevar"},{"ns":"seg_1441","text":""},{"ns":"seg_1442","text":""},{"ns":"seg_1452","text":"ninguna."},{"ns":"seg_1454","text":""},{"ns":"seg_1455","text":"de este tipo de delincuentes"},{"ns":"seg_1457","text":"de las más bajas."},{"ns":"seg_1459","text":"Manuel García Viejo,"},{"ns":"seg_1462","text":""},{"ns":"seg_1464","text":"de la orden hospitalaria"},{"ns":"seg_1466","text":"a la que pertenecía,"},{"ns":"seg_1468","text":"con un funeral en Madrid."},{"ns":"seg_1473","text":"muestra su vocación religiosa,"},{"ns":"seg_1476","text":"su compromiso médico."},{"ns":"seg_1479","text":"llevadas al extremo,"},{"ns":"seg_1482","text":"de la Orden de San Juan de Dios,"},{"ns":"seg_1485","text":""},{"ns":"seg_1500","text":"una ceremonia"},{"ns":"seg_1503","text":"la labor de los misioneros"},{"ns":"seg_1505","text":""},{"ns":"seg_1507","text":""},{"ns":"seg_1508","text":"de Sierra Leona."},{"ns":"seg_1511","text":"dedicó 32 años de su vida."},{"ns":"seg_1524","text":"entrega,el amor"},{"ns":"seg_1529","text":"la esperanza."},{"ns":"seg_1542","text":"el virus del Ébola no da tregua."},{"ns":"seg_1544","text":""},{"ns":"seg_1546","text":"el número de muertos"},{"ns":"seg_1549","text":"o sospechosos de tener"},{"ns":"seg_1552","text":""},{"ns":"seg_1554","text":"Liberia es el país"},{"ns":"seg_1556","text":"de Sierra Leona y Guinea."},{"ns":"seg_1559","text":"destinará de manera inmediata,"},{"ns":"seg_1564","text":"de unos 102 millones de euros"},{"ns":"seg_1566","text":""},{"ns":"seg_1570","text":"afectadopor el Ébola"},{"ns":"seg_1572","text":"está curado."},{"ns":"seg_1574","text":""},{"ns":"seg_1576","text":"cuando trabajaba como voluntario"},{"ns":"seg_1579","text":""},{"ns":"seg_1581","text":"aunque extremadamente débil,"},{"ns":"seg_1587","text":""},{"ns":"seg_1589","text":"en el hospital."},{"ns":"seg_1591","text":"que está libre del virus."},{"ns":"seg_1594","text":"con uno de los nuevos fármacos"},{"ns":"seg_1597","text":"el TKM-Ébola,"},{"ns":"seg_1600","text":""},{"ns":"seg_1601","text":"y en voluntarios humanos,"},{"ns":"seg_1604","text":"genético del virus;"},{"ns":"seg_1607","text":"ha recibido transfusiones de sangre"},{"ns":"seg_1609","text":""},{"ns":"seg_1611","text":"Ken Bradley,"},{"ns":"seg_1613","text":""},{"ns":"seg_1615","text":"se cree que ahora es inmune"},{"ns":"seg_1618","text":""},{"ns":"seg_1621","text":"curar a tres pacientes"},{"ns":"seg_1622","text":""},{"ns":"seg_1624","text":"la información"},{"ns":"seg_1626","text":"de los países más afectados."},{"ns":"seg_1628","text":"que casi no hay existencia"},{"ns":"seg_1630","text":"que han tenido éxito en este país."},{"ns":"seg_1633","text":"también con una nueva vacuna,"},{"ns":"seg_1636","text":"resultados definitivos."},{"ns":"seg_1638","text":"y ahora Rick Sacra"},{"ns":"seg_1642","text":"han asistido esta mañana"},{"ns":"seg_1644","text":"de Álvaro del Portillo,"},{"ns":"seg_1646","text":"José María Escribá de Balaguer."},{"ns":"seg_1649","text":"han llegado fieles de todo el mundo,"},{"ns":"seg_1651","text":""},{"ns":"seg_1653","text":"y nos cuentan"},{"ns":"seg_1656","text":"en honor a Alvaro del Portillo,"},{"ns":"seg_1658","text":"presidida"},{"ns":"seg_1660","text":"el delegado del papa Francisco."},{"ns":"seg_1664","text":"el escenario de una ceremonia"},{"ns":"seg_1667","text":"jóvenes de todo el mundo."},{"ns":"seg_1685","text":"un mensaje del papa"},{"ns":"seg_1688","text":"como un hombre"},{"ns":"seg_1690","text":"de la discordia."},{"ns":"seg_1701","text":"han asistido esta mañana"},{"ns":"seg_1703","text":"de Álvaro del Portillo."},{"ns":"seg_1706","text":"por 150 obispos de todo el mundo"},{"ns":"seg_1709","text":"de televisión."},{"ns":"seg_1719","text":"han sido acreditados"},{"ns":"seg_1729","text":"han sido acreditados"},{"ns":"seg_1731","text":""},{"ns":"seg_1734","text":"de las Personas Sordas."},{"ns":"seg_1736","text":"\"Que lo escuche todo el mundo\","},{"ns":"seg_1739","text":"han salido a la calle."},{"ns":"seg_1742","text":"las barreras a las que se enfrenta"},{"ns":"seg_1744","text":"tienen alguna deficiencia auditiva"},{"ns":"seg_1748","text":"para que logren"},{"ns":"seg_1750","text":""},{"ns":"seg_1751","text":"y más recursos"},{"ns":"seg_1753","text":"y la comunicación oral."},{"ns":"seg_1761","text":"del teléfono 2 millones Pues esto"},{"ns":"seg_1764","text":"simple llamada de teléfono porque"},{"ns":"seg_1767","text":"simplemente para avisar de"},{"ns":"seg_1769","text":"que ir a un bar y pedir"},{"ns":"seg_1779","text":""},{"ns":"seg_1781","text":"40 personas sudan por sacar adelante"},{"ns":"seg_1784","text":"en España."},{"ns":"seg_1788","text":""},{"ns":"seg_1790","text":"pero sin subtítulos,"},{"ns":"seg_1792","text":"y me dedicaba a contemplarla"},{"ns":"seg_1795","text":"Cuando tenía 9 años,"},{"ns":"seg_1797","text":"algunos contenidos a través"},{"ns":"seg_1799","text":"Por fin podía enterarme"},{"ns":"seg_1803","text":"las voces ya que los subtítulos,"},{"ns":"seg_1806","text":"diferente color."},{"ns":"seg_1810","text":""},{"ns":"seg_1812","text":"que me explicase qué decía la tele."},{"ns":"seg_1815","text":""},{"ns":"seg_1817","text":"Por ejemplo puedo ir con mi portátil"},{"ns":"seg_1819","text":"y hablamos por vídeconferencia"},{"ns":"seg_1823","text":"Tener esa posibilidasd de hacer una"},{"ns":"seg_1826","text":"Es una alegría que las cosas"},{"ns":"seg_1828","text":"El avance de las nuevas tecnologías"},{"ns":"seg_1832","text":"pero, aún en el siglo XXI,"},{"ns":"seg_1835","text":"pero, aún en el siglo XXI,"},{"ns":"seg_1838","text":"vida normalizada."},{"ns":"seg_1840","text":""},{"ns":"seg_1841","text":"que superar en su día a día."},{"ns":"seg_1850","text":"de uso compartido de vehículos UBER"},{"ns":"seg_1852","text":"en Madrid hasta que no acredite"},{"ns":"seg_1855","text":"para operar como intermediarios"},{"ns":"seg_1858","text":""},{"ns":"seg_1859","text":"le ha pedido a la empresa"},{"ns":"seg_1861","text":"necesaria en un plazo de 10 días."},{"ns":"seg_1864","text":"si la plataforma que conecta"},{"ns":"seg_1866","text":"y usuarios podrá trabajar"},{"ns":"seg_1869","text":""},{"ns":"seg_1870","text":"en Bélgica y en Londres."},{"ns":"seg_1872","text":"en Alemania en un limbo jurídico"},{"ns":"seg_1875","text":""},{"ns":"seg_1876","text":""},{"ns":"seg_1878","text":"la prohibió hace tres semanas,"},{"ns":"seg_1880","text":"que no había motivos"},{"ns":"seg_1882","text":"de urgencia."},{"ns":"seg_1884","text":"en los tribunales,"},{"ns":"seg_1887","text":"los taxistas están a la caza"},{"ns":"seg_1889","text":"y los denuncian, uno por uno,"},{"ns":"seg_1892","text":"Hamburgo, Múnich,"},{"ns":"seg_1894","text":"donde está implantada."},{"ns":"seg_1897","text":""},{"ns":"seg_1899","text":"sin licencia como ilegal,"},{"ns":"seg_1902","text":"a no prestar servicios"},{"ns":"seg_1905","text":"y retirada del carnet."},{"ns":"seg_1909","text":"que nadie discute"},{"ns":"seg_1912","text":""},{"ns":"seg_1915","text":"repartidos por la ciudad,"},{"ns":"seg_1917","text":""},{"ns":"seg_1919","text":"y puedes dejar el coche"},{"ns":"seg_1925","text":"y puedes dejar el coche"},{"ns":"seg_1928","text":"de un círculo en la ciudad"},{"ns":"seg_1931","text":"y aparcamientos."},{"ns":"seg_1936","text":"de San Sebastían hoy toca palmarés"},{"ns":"seg_1938","text":"la francesa \"Samba\""},{"ns":"seg_1941","text":""},{"ns":"seg_1943","text":"con la que sus directores"},{"ns":"seg_1945","text":"de su anterior trabajo \"Intocable\""},{"ns":"seg_1947","text":""},{"ns":"seg_1949","text":"premio Donostia, Benicio del Toro."},{"ns":"seg_1957","text":"había sido intensa..."},{"ns":"seg_1960","text":"escuchaba todavía los ecos"},{"ns":"seg_1963","text":"en la entrega del premio Donostia..."},{"ns":"seg_1968","text":"que reconoce la versatilidad"},{"ns":"seg_1971","text":"una lista de ilustres nombres."},{"ns":"seg_1994","text":"Del toro presenta aquí Escobar,"},{"ns":"seg_1996","text":"colombiano,"},{"ns":"seg_1998","text":"después del che que vuelve a bordar."},{"ns":"seg_2017","text":"sombras."},{"ns":"seg_2022","text":"esta noche no pueden ser vistos."},{"ns":"seg_2024","text":"y Loreak, suenan a premio,"},{"ns":"seg_2026","text":"sabor español,"},{"ns":"seg_2028","text":"se lleva seguro ya"},{"ns":"seg_2030","text":""},{"ns":"seg_2032","text":"y los Relatos Salvajes"},{"ns":"seg_2034","text":""},{"ns":"seg_2035","text":"del público que al final"},{"ns":"seg_2038","text":"y vida a una película.."},{"ns":"seg_2123","text":"juegan este sábado en la Liga"},{"ns":"seg_2125","text":"el liderato de la liga,"},{"ns":"seg_2127","text":"al Atlético en el Calderón"},{"ns":"seg_2129","text":"desde el banquillo."},{"ns":"seg_2133","text":"entre Athletic y Eibar."},{"ns":"seg_2136","text":"en Television Española."},{"ns":"seg_2138","text":"lucharán por el primer titulo"},{"ns":"seg_2140","text":""},{"ns":"seg_2142","text":"de vitoria para la gran final:"},{"ns":"seg_2145","text":"a las 7 de la tarde,"},{"ns":"seg_2147","text":""},{"ns":"seg_2161","text":"Villarreal - Real Madrid..."},{"ns":"seg_2164","text":"para un jugador del equipo blanco:"},{"ns":"seg_2166","text":""},{"ns":"seg_2167","text":"que el galés debutó"},{"ns":"seg_2169","text":""},{"ns":"seg_2173","text":"y además se estrenó con un gol."},{"ns":"seg_2177","text":"con una tarjeta de visita 4 goles"},{"ns":"seg_2182","text":""},{"ns":"seg_2200","text":"de este otro."},{"ns":"seg_2202","text":"gol blanco en El Madrigal"},{"ns":"seg_2205","text":"del precio puesta,"},{"ns":"seg_2207","text":""},{"ns":"seg_2208","text":"a su nombre."},{"ns":"seg_2210","text":"del Gareth de hoy se espera."},{"ns":"seg_2213","text":"pasado puede mejorarlo este año."},{"ns":"seg_2215","text":"pasado puede mejorarlo este año."},{"ns":"seg_2217","text":"y uno en champions,"},{"ns":"seg_2219","text":"cómo no, Cristiano Ronaldo."},{"ns":"seg_2222","text":""},{"ns":"seg_2223","text":"en apenas tres partidos"},{"ns":"seg_2226","text":"con su voracidad."},{"ns":"seg_2228","text":"y 1 al Basilea."},{"ns":"seg_2231","text":""},{"ns":"seg_2234","text":"prueba"},{"ns":"seg_2237","text":"aún sin Cheryshev,"},{"ns":"seg_2239","text":""},{"ns":"seg_2240","text":"del miedo."},{"ns":"seg_2242","text":"esta liga,"},{"ns":"seg_2244","text":"su 9 en la espalda y en la pizarra,"},{"ns":"seg_2247","text":""},{"ns":"seg_2251","text":"el Barça, en el Camp Nou,"},{"ns":"seg_2253","text":""},{"ns":"seg_2255","text":"Leo Messi,"},{"ns":"seg_2258","text":"como profesional,"},{"ns":"seg_2260","text":"con el Barça"},{"ns":"seg_2262","text":""},{"ns":"seg_2266","text":"y ante un rival siempre especial"},{"ns":"seg_2269","text":"en la ultima visita del Granada,"},{"ns":"seg_2271","text":"de oro."},{"ns":"seg_2274","text":"en Granada"},{"ns":"seg_2276","text":"como culé."},{"ns":"seg_2279","text":"como también lo fue"},{"ns":"seg_2280","text":"conjunto nazarí al Camp Nou,"},{"ns":"seg_2283","text":""},{"ns":"seg_2285","text":"superó a Cesar"},{"ns":"seg_2287","text":"en partido oficial."},{"ns":"seg_2291","text":"en modo asistente,"},{"ns":"seg_2293","text":""},{"ns":"seg_2295","text":"que vuelve al equipo."},{"ns":"seg_2298","text":"es el debate"},{"ns":"seg_2304","text":"de Xavi."},{"ns":"seg_2307","text":"tengo un grupo de jugadores,"},{"ns":"seg_2310","text":""},{"ns":"seg_2311","text":""},{"ns":"seg_2312","text":""},{"ns":"seg_2314","text":"con la ilusión por bandera."},{"ns":"seg_2327","text":""},{"ns":"seg_2328","text":"recibe a otro colíder, el Sevilla."},{"ns":"seg_2331","text":"están marcadas por el dia"},{"ns":"seg_2334","text":""},{"ns":"seg_2335","text":"de España desde todo el pais"},{"ns":"seg_2337","text":""},{"ns":"seg_2341","text":"de los deportistas no es nuevo:"},{"ns":"seg_2344","text":"Fernando Torres o Lebron James."},{"ns":"seg_2348","text":""},{"ns":"seg_2352","text":"en el centro,"},{"ns":"seg_2355","text":"con el que juega con Croacia"},{"ns":"seg_2357","text":"en el Atlético de Madrid"},{"ns":"seg_2362","text":"lo vimos ajustándose la máscara."},{"ns":"seg_2365","text":""},{"ns":"seg_2367","text":"es de última generación,"},{"ns":"seg_2369","text":"y hecha a medida,"},{"ns":"seg_2372","text":"tras la factura de nariz"},{"ns":"seg_2374","text":"hace 10 días."},{"ns":"seg_2380","text":""},{"ns":"seg_2381","text":"en el banquillo"},{"ns":"seg_2383","text":"castigado entre cristales."},{"ns":"seg_2386","text":"se han movilizado"},{"ns":"seg_2388","text":""},{"ns":"seg_2389","text":"en el minuto 14,"},{"ns":"seg_2392","text":"como jugador rojiblanco."},{"ns":"seg_2394","text":"que hacerle olvidar los silbidos"},{"ns":"seg_2397","text":"contra el Celta."},{"ns":"seg_2402","text":""},{"ns":"seg_2404","text":"con el Valencia y el Barcelona."},{"ns":"seg_2409","text":""},{"ns":"seg_2410","text":"en la jornada 5,"},{"ns":"seg_2413","text":"todavía no conoce la derrota."},{"ns":"seg_2425","text":"se han quedado en casa"},{"ns":"seg_2427","text":""},{"ns":"seg_2430","text":"en San Namés,"},{"ns":"seg_2432","text":"en Primera División."},{"ns":"seg_2433","text":""},{"ns":"seg_2435","text":""},{"ns":"seg_2437","text":"de la clasificación,"},{"ns":"seg_2439","text":"y tres derrotas seguidas."},{"ns":"seg_2442","text":"es el mejor equipo vasco de la Liga."},{"ns":"seg_2446","text":""},{"ns":"seg_2449","text":""},{"ns":"seg_2451","text":"a su victoria de anoche"},{"ns":"seg_2454","text":""},{"ns":"seg_2455","text":""},{"ns":"seg_2457","text":"para que Nolito remate a placer."},{"ns":"seg_2460","text":"y sus compañeros"},{"ns":"seg_2463","text":"el empate en el minuto 90."},{"ns":"seg_2466","text":""},{"ns":"seg_2469","text":"y ninguna derrota."},{"ns":"seg_2472","text":"del Elche."},{"ns":"seg_2496","text":"en el baloncesto ACB."},{"ns":"seg_2498","text":""},{"ns":"seg_2500","text":"la final de la supercopa."},{"ns":"seg_2502","text":"el Real Madrid."},{"ns":"seg_2504","text":"al Valencia Basket por 13 puntos"},{"ns":"seg_2508","text":"del equipo local, el Laboral Kutxa."},{"ns":"seg_2511","text":"y ganó por 29 puntos."},{"ns":"seg_2514","text":"esta tarde la final número 17"},{"ns":"seg_2518","text":"en una competición ACB."},{"ns":"seg_2521","text":"fichaje, Tómas Satoransky"},{"ns":"seg_2524","text":""},{"ns":"seg_2525","text":"vuelven a citarse en una final,"},{"ns":"seg_2527","text":"y en la última Copa del Rey."},{"ns":"seg_2534","text":"nos conocemos ya todos un poquito"},{"ns":"seg_2537","text":""},{"ns":"seg_2539","text":"este primer titulo de la temporada"},{"ns":"seg_2543","text":""},{"ns":"seg_2546","text":"desde el principio"},{"ns":"seg_2549","text":"pues te puede pasar por encima"},{"ns":"seg_2552","text":"muy fuertes."},{"ns":"seg_2555","text":"por levantar"},{"ns":"seg_2557","text":""},{"ns":"seg_2559","text":""},{"ns":"seg_2562","text":"son nuestros comentaristas,"},{"ns":"seg_2567","text":""},{"ns":"seg_2569","text":"la temporada."},{"ns":"seg_2580","text":""},{"ns":"seg_2597","text":"costó mucho ganar al Valencia."},{"ns":"seg_2605","text":"tiene el equipo más conjuntado"},{"ns":"seg_2609","text":""},{"ns":"seg_2612","text":"1 gran partido estatal de las 7."},{"ns":"seg_2637","text":"Instituto."},{"ns":"seg_2640","text":""},{"ns":"seg_2648","text":"triples a los mejores tiradores."},{"ns":"seg_2655","text":"vez en la vida."},{"ns":"seg_2660","text":"diarias"},{"ns":"seg_2664","text":"esquina."},{"ns":"seg_2670","text":""},{"ns":"seg_2698","text":"no entra más."},{"ns":"seg_2705","text":""},{"ns":"seg_2706","text":"a la selección femenina"},{"ns":"seg_2707","text":"del Mundial de Turquía ante Japón"},{"ns":"seg_2711","text":"viendo en Teledeporte."},{"ns":"seg_2715","text":"es de Japón"},{"ns":"seg_2717","text":"en el llamado grupo de la muerte."},{"ns":"seg_2720","text":""},{"ns":"seg_2733","text":"falta de entendimiento"},{"ns":"seg_2737","text":""},{"ns":"seg_2741","text":"en la concentración de la selección"},{"ns":"seg_2743","text":"del año pasado,"},{"ns":"seg_2745","text":"en general y mucha concentracion"},{"ns":"seg_2748","text":"y estos nueve hombres"},{"ns":"seg_2751","text":""},{"ns":"seg_2752","text":"suficiente exigente"},{"ns":"seg_2754","text":"a los ciclistas españoles."},{"ns":"seg_2759","text":"que hubiese un circuito"},{"ns":"seg_2761","text":""},{"ns":"seg_2765","text":"eso segurisimo."},{"ns":"seg_2768","text":"la dará la propia carrera"},{"ns":"seg_2772","text":"la dará la propia carrera"},{"ns":"seg_2774","text":"ofrecerse en ella."},{"ns":"seg_2778","text":"una situación como la del año pasado"},{"ns":"seg_2781","text":"una situación como la del año pasado"},{"ns":"seg_2783","text":""},{"ns":"seg_2785","text":"que no tenga el mismo final."},{"ns":"seg_2787","text":"español"},{"ns":"seg_2789","text":""},{"ns":"seg_2791","text":""},{"ns":"seg_2792","text":""},{"ns":"seg_2796","text":"de 18 kilometros"},{"ns":"seg_2799","text":""},{"ns":"seg_2801","text":"de 2015."},{"ns":"seg_2806","text":"de salida del GP de Aragón."},{"ns":"seg_2808","text":""},{"ns":"seg_2813","text":""},{"ns":"seg_2814","text":""},{"ns":"seg_2816","text":""},{"ns":"seg_2817","text":"y aunque gane Marc Márquez"},{"ns":"seg_2819","text":""},{"ns":"seg_2819","text":"de Motogp de forma matemática."},{"ns":"seg_2824","text":""},{"ns":"seg_2826","text":"de la Ryder Cup."},{"ns":"seg_2829","text":"esta mañana, Europa."},{"ns":"seg_2831","text":""},{"ns":"seg_2836","text":"ha descansado"},{"ns":"seg_2838","text":""},{"ns":"seg_2847","text":"ha acabado en la décima posición"},{"ns":"seg_2850","text":"rítmica"},{"ns":"seg_2852","text":""},{"ns":"seg_2854","text":"español que quiere subirse al podio"},{"ns":"seg_2858","text":""},{"ns":"seg_2862","text":"con el 23 de los cavaliers."},{"ns":"seg_2865","text":"a jugar en la NBA y ojo"},{"ns":"seg_2868","text":"Lebron James, Kevin Love"},{"ns":"seg_2871","text":""},{"ns":"seg_2872","text":"el entrenador campeón de Europa"},{"ns":"seg_2875","text":""},{"ns":"seg_2879","text":"una clasificación histórica."},{"ns":"seg_2881","text":"de los Kansas City Royals de beisbol"},{"ns":"seg_2887","text":"para el playoff"},{"ns":"seg_2889","text":"¡después de 29 años!"},{"ns":"seg_2913","text":""},{"ns":"seg_2914","text":"miles de conciertos"},{"ns":"seg_2916","text":"de todas las edades."},{"ns":"seg_2919","text":"en la Plaza de las Ventas"},{"ns":"seg_2922","text":""},{"ns":"seg_2924","text":"que nosotros nos hacemos"},{"ns":"seg_2926","text":"¿qué es Rosendo?"},{"ns":"seg_2939","text":"Ñu y Leño,"},{"ns":"seg_2941","text":"soy el primero."},{"ns":"seg_2948","text":"te paraban en la calle."},{"ns":"seg_2951","text":""},{"ns":"seg_2952","text":""},{"ns":"seg_2961","text":""},{"ns":"seg_2963","text":"a la libertad."},{"ns":"seg_2966","text":"y la persistencia."},{"ns":"seg_2968","text":"en lo más alto."},{"ns":"seg_2970","text":""},{"ns":"seg_2973","text":"el guitarrista y el escritor,"},{"ns":"seg_2977","text":"el guitarrista y el escritor,"},{"ns":"seg_2980","text":"probablemente de los tipos"},{"ns":"seg_2984","text":"en este país,"},{"ns":"seg_2987","text":""},{"ns":"seg_2989","text":"y ahora más de 10.000 firmas"},{"ns":"seg_2992","text":"piden que sea una estatua."},{"ns":"seg_2994","text":""},{"ns":"seg_3008","text":""},{"ns":"seg_3011","text":"porque yo creo que este tipo"},{"ns":"seg_3020","text":""},{"ns":"seg_3022","text":"lo que ha dicho"},{"ns":"seg_3023","text":""},{"ns":"seg_3051","text":"con la de Prince,"},{"ns":"seg_3053","text":"dos nuevos discos."},{"ns":"seg_3055","text":"con su nueva banda."},{"ns":"seg_3057","text":""},{"ns":"seg_3058","text":""}]}