{"url":"http://www.rtve.es/alacarta/videos/telediario/telediario-21-horas-13-09-14/2755896/","subtitles":[{"ns":"seg_14","text":"A esta hora, en Almansa, entre Albacete y Murcia,"},{"ns":"seg_16","text":"un incendio ha arrasado ya cientos de hectáreas."},{"ns":"seg_19","text":"El fuego que se ha declarado en un paraje escarpado"},{"ns":"seg_22","text":"y se ha extendido muy rápido."},{"ns":"seg_24","text":"La Junta de Castilla-La Mancha ha decretado"},{"ns":"seg_26","text":"el nivel 1 de emergencia por su proximidad a núcleos urbanos."},{"ns":"seg_29","text":"Algunos vecinos han tenido que ser desalojados."},{"ns":"seg_31","text":"Y, según acabamos de saber,"},{"ns":"seg_33","text":"uno de los helicópteros que participaban en la extinción"},{"ns":"seg_35","text":"ha tenido un accidente."},{"ns":"seg_37","text":"Y podría haber un fallecido."},{"ns":"seg_41","text":"Buenas noches."},{"ns":"seg_42","text":"A lo largo del Telediario les ampliaremos más datos"},{"ns":"seg_44","text":"sobre lo ocurrido."},{"ns":"seg_45","text":"En la crónica política,"},{"ns":"seg_47","text":"Pedro Sánchez ha confirmado de forma oficial"},{"ns":"seg_49","text":"que se presentará a las elecciones primarias de su partido"},{"ns":"seg_51","text":"para aspirar a la presidencia del Gobierno."},{"ns":"seg_53","text":"Buenas noches."},{"ns":"seg_54","text":"Lo ha dicho durante el comité federal del PSOE."},{"ns":"seg_59","text":"El calendario de primarias para las elecciones municipales"},{"ns":"seg_61","text":"y autonómicas de 2015."},{"ns":"seg_63","text":"En su discurso en su primer Comité Federal, el líder del PSOE"},{"ns":"seg_65","text":"cree que el PP se beneficia de lo que llama"},{"ns":"seg_67","text":"\"auge del populismo\"."},{"ns":"seg_72","text":"En la reunión informal del Ecofin para debatir"},{"ns":"seg_74","text":"sobre el actual estancamiento de la economía europea,"},{"ns":"seg_76","text":"Luis De Guindos ha llamado a la autocrítica."},{"ns":"seg_79","text":"El ministro de Economía, sin embargo,"},{"ns":"seg_80","text":"cree que las políticas que se han hecho hasta ahora"},{"ns":"seg_83","text":"no son erróneas."},{"ns":"seg_98","text":"En la zona euro hay una situación de crecimiento económico."},{"ns":"seg_102","text":"Por la tarde, De Guindos ha asistido,"},{"ns":"seg_104","text":"junto a otros representantes políticos,"},{"ns":"seg_106","text":"de la banca y de la empresa, al funeral celebrado en Santander"},{"ns":"seg_108","text":"en memoria de Emilio Botín."},{"ns":"seg_110","text":"La familia del banquero fallecido ha estado arropada"},{"ns":"seg_112","text":"por muchos ciudadanos."},{"ns":"seg_113","text":"Han hablado los padres de James Foley,"},{"ns":"seg_115","text":"el periodista de Estados Unidos que fue decapitado"},{"ns":"seg_117","text":"por el Estado Islámico, y grabado en un vídeo"},{"ns":"seg_120","text":"que se divulgó el 19 de agosto."},{"ns":"seg_121","text":"John y Diane aseguran que el Gobierno les advirtió"},{"ns":"seg_124","text":"que serían perseguidos si pagaban un rescate por su hijo,"},{"ns":"seg_127","text":"y dicen que nunca supieron si había algún plan"},{"ns":"seg_129","text":"para rescatarlo de su secuestro en Siria."},{"ns":"seg_134","text":"Más de 200 camiones con 2000 toneladas de ayuda humanitaria"},{"ns":"seg_137","text":"han llegado hoy a Lugansk, al este de Ucrania, desde Rusia."},{"ns":"seg_140","text":"Kiev se queja de que no han podido revisar su contenido,"},{"ns":"seg_143","text":"y acusa a Moscú de ingerencia."},{"ns":"seg_145","text":"En el aeropuerto de Donetsk han seguido los tiroteos."},{"ns":"seg_150","text":"Festival DCODE esta noche, en Madrid."},{"ns":"seg_152","text":"Es su cuarta edición,"},{"ns":"seg_153","text":"y el festival ofrece música variada en tres escenarios"},{"ns":"seg_156","text":"del Campus de la Universidad Complutense de Madrid."},{"ns":"seg_158","text":"Durante toda la noche, grupos de jazz, rock, o electro pop."},{"ns":"seg_162","text":"Actuación en exclusiva en España de Beck, además de otros conciertos"},{"ns":"seg_166","text":"de Vetusta Morla, Russian Red, entre otros."},{"ns":"seg_174","text":"En los deportes, Arsenio, Marc, esta tarde Contador"},{"ns":"seg_176","text":"ha sentenciado la Vuelta."},{"ns":"seg_178","text":"No hay sorpresas y Alberto Contador es el ganador virtual"},{"ns":"seg_181","text":"de la vuelta ciclista a España."},{"ns":"seg_183","text":"Hoy ha ganado la etapa y mañana, en Santiago de Compostela,"},{"ns":"seg_187","text":"sumará su gran tercer triunfo en la ronda española."},{"ns":"seg_192","text":"Contador salia a defender el liderato en la penultima etapa"},{"ns":"seg_195","text":"y ha acabado atacando y ganando a su principal rival Chris Froome."},{"ns":"seg_198","text":"El ultimo km de Contador subiendo el Alto de Ancares ha sido épico."},{"ns":"seg_202","text":"El podio final será para Contador, Froome y Valverde."},{"ns":"seg_207","text":"Dos goles de Neymar mantienen al Barça líder invicto en la liga."},{"ns":"seg_210","text":"Tres partidos y tres victorias."},{"ns":"seg_212","text":"El barcelona ha ganado por 2 goles a 0"},{"ns":"seg_214","text":"al Athletic Club de Bilbao."},{"ns":"seg_216","text":"Y en estos momento, en el Bernabéu."},{"ns":"seg_219","text":"Se juega el derbi madrileño."},{"ns":"seg_236","text":"El lider del PSOE cree que hay una coalición de intereses"},{"ns":"seg_239","text":"entre el PP y Podemos,"},{"ns":"seg_241","text":"al que no ha mencionado, para dividir a la izquierda."},{"ns":"seg_243","text":"Lo ha dicho en su primer Comité Federal"},{"ns":"seg_245","text":"como secretario general."},{"ns":"seg_246","text":"Una reunión en la que también ha oficializado su candidatura"},{"ns":"seg_249","text":"a la presidencia del Gobierno."},{"ns":"seg_252","text":"El PSOE es el partido del cambio que necesita España,"},{"ns":"seg_254","text":"dice su secretario general."},{"ns":"seg_256","text":"Un proyecto lejos del PP y de Podemos,"},{"ns":"seg_258","text":"al que no menciona expresamente."},{"ns":"seg_260","text":"Pero para futuras alianzas, la minoritaria Izquierda Socialista"},{"ns":"seg_264","text":"no quiere que se cierre la puerta a Podemos."},{"ns":"seg_266","text":"Y los andaluces rechazan calificarlo de populismo."},{"ns":"seg_270","text":"Pero Sanchez, según algunas fuentes, asegura que el adversario es elPP"},{"ns":"seg_274","text":"y ha advertido que usan a Podemos para dividir a la Izquierda"},{"ns":"seg_278","text":"\"A mi me gustaría denunciar gran coalición de intereses"},{"ns":"seg_281","text":"entre los extremos."},{"ns":"seg_283","text":"Hay un partido que se frota las manos"},{"ns":"seg_286","text":"ante el auge del populismo, y es el PP."},{"ns":"seg_291","text":"Y la explicación es sencilla:"},{"ns":"seg_292","text":"saben que ante el naufragio de su proyecto"},{"ns":"seg_294","text":"la única manera que tienen de perpetuarse es muy sencilla:"},{"ns":"seg_297","text":"debilitar al Partido Socialista Obrero español\""},{"ns":"seg_300","text":"Otra cuestión a debate: Cataluña."},{"ns":"seg_302","text":"Sanchez ha reiterado su propuesta de reforma federal y diálogo"},{"ns":"seg_305","text":"entre Rajoy y Mas."},{"ns":"seg_307","text":"\"Le pido al señor Rajoy que abra una puerta a la esperanza"},{"ns":"seg_310","text":"a la convivencia, a la unión de España,"},{"ns":"seg_314","text":"afrontando un proceso de reforma, de renovación constitucional"},{"ns":"seg_316","text":"entre todos."},{"ns":"seg_318","text":"Si hace eso, si el señor Rajoy es valiente, que no le quepa duda"},{"ns":"seg_322","text":"que el PSOE estará a su lado\"."},{"ns":"seg_325","text":"Y defiende una oposición ciudadana que logre, por ejemplo,"},{"ns":"seg_328","text":"que no salga la reforma de la ley del aborto"},{"ns":"seg_330","text":"ni la elección directa de alcaldes."},{"ns":"seg_332","text":"Se ha aprobado las primarias a autonomías y ayuntamientos"},{"ns":"seg_335","text":"entre octubre y noviembre."},{"ns":"seg_336","text":"Y a la presidencia del Gobierno, en julio, y con primer nombre,"},{"ns":"seg_339","text":"de momento: Pedro Sánchez."},{"ns":"seg_342","text":"En un acto de Nuevas Generaciones del PP en Valencia,"},{"ns":"seg_345","text":"Esteban González Pons se ha referido al líder"},{"ns":"seg_347","text":"de los socialistas,"},{"ns":"seg_349","text":"al que ha comparado con el expresidente Zapatero."},{"ns":"seg_353","text":"Para Esteban González Pons el PSOE ha cambiado de líder"},{"ns":"seg_355","text":"pero no de estilo."},{"ns":"seg_356","text":"Asegura que Pedro Sánchez es un político de conveniencia"},{"ns":"seg_359","text":"y no de convicción."},{"ns":"seg_361","text":"Pedro Sánchez habla bonito como Zapatero,"},{"ns":"seg_365","text":"Pedro Sánchez dice lo que quieres oir como Zapatero,"},{"ns":"seg_370","text":"y Pedro Sánchez si llega a gobernar nos arruinará"},{"ns":"seg_374","text":"como nos arruinó Zapatero."},{"ns":"seg_377","text":"En la clausura del Foro Nacional de Nuevas Generaciones,"},{"ns":"seg_380","text":"González Pons ha elogiado las reformas"},{"ns":"seg_381","text":"del Gobierno gracias a las cuales dice"},{"ns":"seg_384","text":"está garantizado el estado del bienestar."},{"ns":"seg_386","text":"Y asegura que países como Francia e Italia"},{"ns":"seg_388","text":"van a tener que \"copiar\""},{"ns":"seg_389","text":"las medidas aprobadas por Mariano Rajoy."},{"ns":"seg_392","text":"También ha hablado de la consulta soberanista."},{"ns":"seg_394","text":"Despues del 9N"},{"ns":"seg_396","text":"seguirá habiendo paro, de empresas, impagados,"},{"ns":"seg_406","text":"los problemas de todos seguirán y nada se habrá solucionado."},{"ns":"seg_413","text":"Cree que Artur Mas ha convertido la independencia"},{"ns":"seg_415","text":"en un espejismo para Cataluña y en un callejón sin salida"},{"ns":"seg_418","text":"para los catalanes."},{"ns":"seg_422","text":"En una carta dirigida a la militancia"},{"ns":"seg_424","text":"de Unió Democràtica de Cataluña, el secretario general de CiU,"},{"ns":"seg_427","text":"Ramón Espadaler,"},{"ns":"seg_428","text":"que hace una semana sustituyó a Duran i Lleida en el cargo,"},{"ns":"seg_431","text":"recuerda que su partido, Unió,"},{"ns":"seg_433","text":"apuesta por un modelo de Estado confederal"},{"ns":"seg_435","text":"y no por la independencia"},{"ns":"seg_437","text":"e insiste en defender la consulta soberanista."},{"ns":"seg_439","text":"Sobre estas declaraciones de Espadaler,"},{"ns":"seg_441","text":"que también es consejero de Interior,"},{"ns":"seg_443","text":"le han preguntado esta tarde al portavoz de la Generalitat."},{"ns":"seg_447","text":"Respeto todas las misivas que hagan los partidos"},{"ns":"seg_450","text":"en estos próximos días, simplemente defiendo"},{"ns":"seg_453","text":"como me corresponde en nombre del Gobierno"},{"ns":"seg_456","text":"de la Generalitat de Cataluña"},{"ns":"seg_458","text":"el programa electoral que compartimos,"},{"ns":"seg_460","text":"el acuerdo de legislatura"},{"ns":"seg_462","text":"que dio lugar al Gobierno de la Generalitat actual"},{"ns":"seg_464","text":"y no otras consideraciones."},{"ns":"seg_467","text":"En el caso de supuesto fraude de los cursos de formación,"},{"ns":"seg_469","text":"la juez Alaya ha imputado"},{"ns":"seg_471","text":"al exconsejero de Hacienda de la Junta de Andalucía,"},{"ns":"seg_473","text":"Ángel Ojeda."},{"ns":"seg_475","text":"Le acusa de dos presuntos delitos, uno continuado de prevaricacion"},{"ns":"seg_478","text":"y otro de malversación de caudales públicos."},{"ns":"seg_480","text":"Según el auto, el exconsejero habría utilizado sus influencias"},{"ns":"seg_484","text":"para conseguir más de 33 millones de euros en subvenciones."},{"ns":"seg_487","text":"Ojeda fue detenido, junto a otras ocho personas,"},{"ns":"seg_489","text":"a principios de agosto en Sanlúcar de Barrameda, en Cádiz,"},{"ns":"seg_492","text":"por este caso."},{"ns":"seg_493","text":"Entonces el juez le dejó en libertad con cargos."},{"ns":"seg_500","text":"Reunión informal del Ecofin en Milán para debatir"},{"ns":"seg_502","text":"sobre el actual estancamiento de la economía europea."},{"ns":"seg_505","text":"El ministro De Guindos cree ç"},{"ns":"seg_507","text":"que no todas las políticas de los últimos años"},{"ns":"seg_509","text":"han sido erróneas, pero cree que la situación actual"},{"ns":"seg_512","text":"\"tiene que hacer pensar\"."},{"ns":"seg_514","text":"Europa trata de eludir una nueva recesión."},{"ns":"seg_517","text":"Para lograrlo sigue apostando por las reformas estructurales,"},{"ns":"seg_520","text":"pero también por un impulso a la inversión."},{"ns":"seg_524","text":"Los ministros de Economía han puesto hoy sobre la mesa"},{"ns":"seg_527","text":"el plan de 300.000 millones de euros anunciado por Juncker"},{"ns":"seg_530","text":"para los primeros meses del próximo año."},{"ns":"seg_533","text":"En cuanto a las reformas, la Comisión recuerda"},{"ns":"seg_536","text":"sus positivos efectos en algunos países."},{"ns":"seg_543","text":"Luis de Guindos ha defendido una nueva estrategia económica,"},{"ns":"seg_546","text":"capaz de hacer autocrítica y de aprender"},{"ns":"seg_549","text":"de los errores del pasado."},{"ns":"seg_561","text":"En la zona euro y una situación de crecimiento económico"},{"ns":"seg_565","text":"que creo que nos debe hacer pensar."},{"ns":"seg_582","text":"Francia e Italia son ahora mismo los países que concentran"},{"ns":"seg_584","text":"todas las miradas."},{"ns":"seg_586","text":"Sus malos resultados económicos, unidos a los de Alemania,"},{"ns":"seg_588","text":"han provocado el estancamiento de la zona euro."},{"ns":"seg_590","text":"A ellos les corresponde ahora tomar la iniciativa."},{"ns":"seg_592","text":"Después de la reunión del Ecofin de Milán,"},{"ns":"seg_594","text":"el ministro Luis de Guindos ha viajado hasta Santander."},{"ns":"seg_597","text":"Allí ha asistido, en representación del Gobierno,"},{"ns":"seg_599","text":"al funeral de Emilio Botín."},{"ns":"seg_601","text":"Al funeral, celebrado en la catedral de la capital cántabra,"},{"ns":"seg_604","text":"ha asistido una numerosa representación"},{"ns":"seg_605","text":"del mundo de la política, de la banca y la empresa,"},{"ns":"seg_608","text":"entre otros ámbitos."},{"ns":"seg_609","text":"También muchos ciudadanos han querido arropar a la familia"},{"ns":"seg_612","text":"de Emilio Botín."},{"ns":"seg_614","text":"Centenares de santanderinos"},{"ns":"seg_616","text":"han querido dar su último adiós a Emilio Botín"},{"ns":"seg_618","text":"que fue presidente del Banco Santander durante 28 años."},{"ns":"seg_621","text":"Aplausos para recibir y también para despedir a su familia"},{"ns":"seg_624","text":"en la puerta de la catedral de Santander"},{"ns":"seg_626","text":"en un funeral en el que también han estado representados"},{"ns":"seg_629","text":"los Gobiernos anteriores, con los exvicepresidentes"},{"ns":"seg_632","text":"Rodrigo Rato, que estuvo también al frente de Caja Madrid,"},{"ns":"seg_635","text":"y Teresa Fernández de la Vega que ha destacado"},{"ns":"seg_638","text":"no sólo la labor en el sector financiero"},{"ns":"seg_640","text":"sino también el compromiso social con la educación y la cultura"},{"ns":"seg_644","text":"de Emilio Botín."},{"ns":"seg_645","text":"Los presidente de la Caixa, Bankia, Telefónica, Inditex o Sacyr"},{"ns":"seg_648","text":"también han estado en Santander para despedir al banquero."},{"ns":"seg_651","text":"La agenda de la entidad continúa y su nueva presidenta, Ana Botín,"},{"ns":"seg_655","text":"primogénita del fallecido,"},{"ns":"seg_657","text":"presidirá la Junta de accionistas del próximo lunes, aquí en Santander"},{"ns":"seg_671","text":"Es el aeropuerto de Donetsk, en el este de Ucrania,"},{"ns":"seg_673","text":"durante los enfrentamientos de hoy."},{"ns":"seg_675","text":"El Gobierno de Kiev asegura que ha repelido los ataques"},{"ns":"seg_678","text":"de los separatistas contra las instalaciones."},{"ns":"seg_680","text":"Estos combates, aunque aislados, amenazan la frágil tregua pactada"},{"ns":"seg_684","text":"entre los dos bandos el viernes de la semana pasada."},{"ns":"seg_694","text":"Rusia acusa a Estados Unidos de querer mantener la crisis"},{"ns":"seg_696","text":"en Ucrania para vender en Europa sus recursos energéticos."},{"ns":"seg_699","text":"El ministro de Exteriores asegura que la intención"},{"ns":"seg_702","text":"es romper los lazos económicos entre Rusia y Europa."},{"ns":"seg_705","text":"Lo ha dicho Luis Pérez un día después"},{"ns":"seg_707","text":"de que occidente aplicara sanciones"},{"ns":"seg_708","text":"contra sectores estratégicos."},{"ns":"seg_730","text":"La respuesta rusa no se ha dado todavía pero según el ministro de"},{"ns":"seg_735","text":"exteriores"},{"ns":"seg_736","text":"el objetivo de Estados Unidos es muy claro:"},{"ns":"seg_741","text":"romper los lazos económicos entre la Unión Europea y Rusia."},{"ns":"seg_746","text":"Según él lo que pretende Estados Unidos extender a Europa"},{"ns":"seg_750","text":"gas licuado."},{"ns":"seg_756","text":"En el plano militar espera que se mantenga el alto el fuego"},{"ns":"seg_762","text":"pactado en la semana pasada en el este de Ucrania."},{"ns":"seg_768","text":"Los dos bandos se acusan mutuamente de romper el alto el fuego"},{"ns":"seg_774","text":"y tanto las tropas leales a Kiev como los separatistas rusos"},{"ns":"seg_778","text":"están reagrupando a sus hombres."},{"ns":"seg_781","text":"El convoy en el que se calcula que hay más de 200 camiones,"},{"ns":"seg_784","text":"llevaba una bandera: la rusa."},{"ns":"seg_786","text":"La policía de fronteras de ese país ha inspeccionado 40 vehículos."},{"ns":"seg_789","text":"El resto ha pasado sin ninguna supervisión."},{"ns":"seg_791","text":"Esta jefa de almacén en Lugansk señala"},{"ns":"seg_793","text":"que se han descargado 8 camiones con arroz, azúcar,"},{"ns":"seg_795","text":"latas de pescado y carne."},{"ns":"seg_797","text":"A pesar de que los acuerdos del alto el fuego"},{"ns":"seg_799","text":"preveían la llegada de ayuda humanitaria,"},{"ns":"seg_801","text":"el portavoz de defensa ucraniano ha denunciado"},{"ns":"seg_804","text":"que el convoy ha pasado sin ningún tipo de control"},{"ns":"seg_806","text":"en Ucrania y sin la supervisión de la Cruz Roja Internacional."},{"ns":"seg_809","text":"Ha dicho que se han producido varios incidentes en el Este,"},{"ns":"seg_812","text":"en los que asegura que ha muerto un militar ucraniano,"},{"ns":"seg_815","text":"otros cinco han resultado heridos, y 12 rebeldes han fallecido"},{"ns":"seg_818","text":"en enfrentamientos con el ejército."},{"ns":"seg_821","text":"\"En caso de emergencia tenemos una zona para refugiarnos,"},{"ns":"seg_824","text":"nosotros y los niños."},{"ns":"seg_825","text":"Todos saben a donde deben dirigirse."},{"ns":"seg_828","text":"Como Yelena, muchos residentes de Mariúpol"},{"ns":"seg_830","text":"se preparan ante posibles enfrentamientos con los rebeldes."},{"ns":"seg_833","text":"Han almacenado agua y víveres básicos."},{"ns":"seg_835","text":"\"esperamos que no ocurra nada, dice Valeria,"},{"ns":"seg_839","text":"pero nos preparamos por si vuelven los ataques\"."},{"ns":"seg_842","text":"Diseñan incluso disfraces de camuflaje"},{"ns":"seg_844","text":"para enviar a los soldados del frente,"},{"ns":"seg_846","text":"para espías del ejército o para francotiradores."},{"ns":"seg_848","text":"También recogen armas y se entrenan para enfrentarse a los prorrusos."},{"ns":"seg_856","text":"En Kiev, durante la Conferencia de Estrategia Europea,"},{"ns":"seg_859","text":"el primer ministro ucraniano, Arseni Yatseniuk,"},{"ns":"seg_861","text":"ha acusado al presidente ruso, Vladímir Putin,"},{"ns":"seg_864","text":"de querer destruir Ucrania como país."},{"ns":"seg_867","text":"La familia de David Haines, el cooperante británico"},{"ns":"seg_870","text":"en manos de los yihadistas del Estado Islámico,"},{"ns":"seg_872","text":"ha pedido a sus captores que se pongan en contacto con ellos."},{"ns":"seg_875","text":"La noticia llega cuando los padres de James Foley,"},{"ns":"seg_878","text":"el periodista estadounidense decapitado por los islamistas,"},{"ns":"seg_880","text":"cuentan en una entrevista"},{"ns":"seg_882","text":"que su Gobierno les amenazo con procesarles"},{"ns":"seg_884","text":"si pagaban un rescate por su hijo."},{"ns":"seg_888","text":"Casi un mes después de conocer la ejecución de su hijo,"},{"ns":"seg_891","text":"John y Diane Foley se lamentan de haber confiado en su Gobierno."},{"ns":"seg_895","text":"\"Pensamos ingenuamente que el Gobierno"},{"ns":"seg_897","text":"se encargaría de traerlo de vuelta."},{"ns":"seg_899","text":"Debimos haber tomado la iniciativa, teníamos que haber hecho algo\","},{"ns":"seg_903","text":"dice la madre del reportero."},{"ns":"seg_905","text":"Sí intentaron recaudar fondos para pagar un rescate."},{"ns":"seg_908","text":"Pero, desde la Administración, les advirtieron"},{"ns":"seg_911","text":"que eso es ilegal en Estados Unidos y que podían ser procesados."},{"ns":"seg_915","text":"\"¿Y qué haces? ¿Dejas a tu hijo prisionero,"},{"ns":"seg_917","text":"mientras le maltratan? De ninguna manera\","},{"ns":"seg_919","text":"se justifica ahora John Foley."},{"ns":"seg_922","text":"\"Me sorprendió que tuvieran tan poca compasión\", añade su mujer."},{"ns":"seg_925","text":"En mayo, la liberación de un soldado preso en Afganistán"},{"ns":"seg_928","text":"a cambio de cinco talibanes detenidos en Guantánamo"},{"ns":"seg_931","text":"desató la polémica en un país que presume de no pagar rescates."},{"ns":"seg_937","text":"La diligencia y la firmeza que prometió Obama"},{"ns":"seg_939","text":"tras la muerte de James Foley, tampoco sirvieron para salvar"},{"ns":"seg_942","text":"a Steven Sotloff."},{"ns":"seg_944","text":"Ahora, en el corredor de la muerte yihadista,"},{"ns":"seg_946","text":"espera el británico David Haines, secuestrado en Siria en 2013."},{"ns":"seg_950","text":"Según la propaganda del Estado Islámico,"},{"ns":"seg_952","text":"será el próximo en morir."},{"ns":"seg_954","text":"Su familia ha pedido a sus secuestradores"},{"ns":"seg_956","text":"que se pongan en contacto con ellos."},{"ns":"seg_961","text":"El jefe de la Diplomacia de Estados Unidos, John Kerry,"},{"ns":"seg_963","text":"ultima la búsqueda de apoyos en el Cairo"},{"ns":"seg_965","text":"para formar una coalición internacional"},{"ns":"seg_967","text":"en contra de la amenaza del Estado Islámico."},{"ns":"seg_970","text":"Según Kerry Egipto es un actor clave para combatir a los yihadistas"},{"ns":"seg_973","text":"porque, como centro intelectual del mundo árabe,"},{"ns":"seg_976","text":"puede influir para desmantelar la ideología de los extremistas."},{"ns":"seg_979","text":"La Liga árabe se ha sumado a la coalición"},{"ns":"seg_981","text":"aunque de momento no se sabe que misión desempeñará cada país."},{"ns":"seg_988","text":"En la capital de Uganda,"},{"ns":"seg_990","text":"las autoridades han detectado una célula terrorista"},{"ns":"seg_992","text":"de la milicia islámica somalí Al Shabab."},{"ns":"seg_994","text":"Lo ha confirmado la Embajada de Estados Unidos,"},{"ns":"seg_996","text":"que desconoce dónde planea atentar."},{"ns":"seg_1012","text":"La embajada norteamericana en Uganda advierte a sus ciudadanos"},{"ns":"seg_1018","text":"que pertenezcan refugiados ante la amenaza de un ataque terrorista."},{"ns":"seg_1029","text":"Desfile de la orden protestante en contra de la independencia de"},{"ns":"seg_1033","text":"Escocia"},{"ns":"seg_1036","text":"el Papa Francisco recordado hoy a los caídos en la Segunda Guerra"},{"ns":"seg_1041","text":"Mundial."},{"ns":"seg_1045","text":"Dice que ya se vive una tercera guerra mundial por partes."},{"ns":"seg_1048","text":"Las inundaciones en India y Pakistán"},{"ns":"seg_1050","text":"mantienen a cerca de 200.000 personas atrapadas."},{"ns":"seg_1052","text":"Al menos 450 personas han muerto"},{"ns":"seg_1054","text":"por las lluvias monzónicas de la última semana"},{"ns":"seg_1056","text":"que, ademas de inundaciones, han provocado corrimientos de tierra"},{"ns":"seg_1060","text":"Miles de personas han sido evacuadas, o han huido de sus casas,"},{"ns":"seg_1063","text":"ante el temor de que llegue el agua"},{"ns":"seg_1064","text":"y se han refugiado en campamentos como éste."},{"ns":"seg_1073","text":"Por primera vez, hombres de negocios y noo científicos y ecologistas,"},{"ns":"seg_1076","text":"hablan del impacto del cambio climático."},{"ns":"seg_1078","text":"Las conclusiones van directas a la cartera,"},{"ns":"seg_1081","text":"a lo que costará a las empresas."},{"ns":"seg_1082","text":"Por ejemplo, se calcula que de aquí al 2050"},{"ns":"seg_1085","text":"costará 100.000 millones de dólares hacer frente"},{"ns":"seg_1088","text":"a los daños en viviendas e infraestructuras"},{"ns":"seg_1090","text":"a causa de las tormentas, inundaciones y olas de calor."},{"ns":"seg_1094","text":"Lo que también saldrá caro para la agricultura,"},{"ns":"seg_1096","text":"la productividad de los campos caerá en un 14%"},{"ns":"seg_1099","text":"y se dispararán los precios de algunos productos."},{"ns":"seg_1103","text":"Los hogares consumirán más energía porque hace más frío en invierno"},{"ns":"seg_1106","text":"y más calor en verano"},{"ns":"seg_1108","text":"y eso costará unos 12.000 millones de dólares más cada año."},{"ns":"seg_1113","text":"Tenemos que actuar ahora para que los que vengan después"},{"ns":"seg_1116","text":"sufran menos el catastrófico efecto del cambio climático,"},{"ns":"seg_1119","text":"dice el exsecretario del Tesoro"},{"ns":"seg_1121","text":"y uno de los promotores de esta iniciativa"},{"ns":"seg_1123","text":"junto al millonario y exalcalde de Nueva York."},{"ns":"seg_1129","text":"Ninguna empresa, ciudad o país, puede permitirse ignorar"},{"ns":"seg_1132","text":"los efectos del cambio climático."},{"ns":"seg_1134","text":"Ha lanzado también el siguiente mensaje"},{"ns":"seg_1137","text":"a sus colegas de los negocios:"},{"ns":"seg_1140","text":"\"Si un empresario quiere dormir tranquilo, debe prepararse ya\"."},{"ns":"seg_1148","text":"En el incendio de Almansa en Albacete"},{"ns":"seg_1150","text":"ha fallecido el piloto de uno de los helicópteros"},{"ns":"seg_1152","text":"que trabajaban en las labores de extinción."},{"ns":"seg_1154","text":"Al parecer la nave ha sufrido un accidente cuando se dirigía"},{"ns":"seg_1157","text":"a recargar agua."},{"ns":"seg_1159","text":"El fuego está arrasando una amplia zona forestal"},{"ns":"seg_1161","text":"entre Almansa y Yecla y amenaza las viviendas."},{"ns":"seg_1168","text":"Ha sido necesario desalojar a varios vecinos"},{"ns":"seg_1170","text":"ante el violento avance de las llamas"},{"ns":"seg_1172","text":"y también se han cortado dos carreteras."},{"ns":"seg_1174","text":"Vamos en directo a la zona del incendio, Araceli Sánchez,"},{"ns":"seg_1177","text":"se confirma el fallecimiento del piloto del helicóptero."},{"ns":"seg_1189","text":"Buenas noches."},{"ns":"seg_1190","text":"Fuentes del gobierno regional de Castilla La Mancha"},{"ns":"seg_1195","text":"han confirmado el fallecimiento de este piloto que participaba"},{"ns":"seg_1200","text":"en las labores de extinción."},{"ns":"seg_1203","text":"El helicóptero iba a recoger agua."},{"ns":"seg_1209","text":"El fuego obligado a desalojar las casas de varios vecinos"},{"ns":"seg_1216","text":"y algunos nos han confirmado que a lo largo de la tarde han podido"},{"ns":"seg_1221","text":"entrar en sus viviendas a recoger enseres básicos."},{"ns":"seg_1225","text":"Se prevé que durante la madrugada se pueda dar por estabilizado"},{"ns":"seg_1230","text":"el incendio."},{"ns":"seg_1233","text":"Van a continuar las labores de refresco."},{"ns":"seg_1243","text":"Minutos antes de las dos de la tarde,"},{"ns":"seg_1245","text":"una enorme columna de humo alertaba del fuego."},{"ns":"seg_1247","text":"El incendio forestal comenzaba en esta zona de bosque de Almansa,"},{"ns":"seg_1250","text":"en Albacete."},{"ns":"seg_1251","text":"Brigadas terrestres y medios aéreos han trabajado intensamente"},{"ns":"seg_1254","text":"durante toda la tarde,"},{"ns":"seg_1256","text":"intentando parar el avance de las llamas en su frente central."},{"ns":"seg_1259","text":"Ha sido en esas labores de extinción"},{"ns":"seg_1260","text":"cuando se ha producido el accidente de uno de los helicópteros,"},{"ns":"seg_1263","text":"que se dirigía a recoger agua a la cercana localidad de Alpera."},{"ns":"seg_1266","text":"El piloto ha muerto, según el Gobierno regional."},{"ns":"seg_1268","text":"La Junta de Castilla-La Mancha ha activado el nivel uno"},{"ns":"seg_1271","text":"del plan de emergencias por la proximidad de la población."},{"ns":"seg_1274","text":"Y al parecer ha sido necesario desalojar a varios vecinos"},{"ns":"seg_1276","text":"que de momento no han regresado a sus casas."},{"ns":"seg_1279","text":"La densa humareda ha obligado además a cortar la circulación"},{"ns":"seg_1281","text":"en la carretera que une Yecla con Almansa."},{"ns":"seg_1285","text":"Así ha quedado el Parque Natural del Montgó"},{"ns":"seg_1287","text":"tras el incendio que comenzó el jueves"},{"ns":"seg_1289","text":"y que ha quemado 444 hectáreas en Dénia y Jávea."},{"ns":"seg_1293","text":"Esta mañana el fuego quedaba controlado."},{"ns":"seg_1296","text":"Pero los bomberos han continuado refrescando la zona"},{"ns":"seg_1298","text":"para evitar que las llamas se reaviven."},{"ns":"seg_1310","text":"Ahora el objetivo es conocer las causas que lo provocaron."},{"ns":"seg_1313","text":"Este paraje natural es una zona de alto valor ecológico"},{"ns":"seg_1315","text":"y muy protegida."},{"ns":"seg_1321","text":"Tenemos que aprender a cuidarlo mucho mejor entre todos"},{"ns":"seg_1326","text":"y trabajar para regenerar el terreno lo antes posible."},{"ns":"seg_1331","text":"Además, la ley nacional de montes de 2003 dice"},{"ns":"seg_1333","text":"que en las zonas forestales quemadas no se puede construir en 30 años."},{"ns":"seg_1337","text":"Los vecinos de la zonas desalojadas hacen ahora recuento de los daños."},{"ns":"seg_1340","text":"Todavía con el susto en el cuerpo."},{"ns":"seg_1352","text":"El sector turístico espera"},{"ns":"seg_1353","text":"que las buenas previsiones para este mes no se vean afectadas"},{"ns":"seg_1356","text":"por la desolación que ha dejado el fuego en este pulmón ecológico"},{"ns":"seg_1359","text":"que es también uno de sus principales"},{"ns":"seg_1361","text":"reclamos turísticos."},{"ns":"seg_1364","text":"En Valencia, esta tarde, se ha venido abajo el falso techo"},{"ns":"seg_1366","text":"del centro comercial Arena."},{"ns":"seg_1368","text":"4 personas, entre ellas un menor, están heridas."},{"ns":"seg_1380","text":"Cuatro personas,entre ellas un menor,ha tenido que ser atendidas"},{"ns":"seg_1385","text":"y trasladados a distintos hospitales tras caerles encima"},{"ns":"seg_1389","text":"del falso techo de este centro comercial."},{"ns":"seg_1396","text":"Su estado no reviste gravedad,según nos confirman."},{"ns":"seg_1401","text":"Según nos confirma los bomberos el techo sea desprendido"},{"ns":"seg_1405","text":"debido a un fallo en la estructura."},{"ns":"seg_1411","text":"Y hoy ha llegado a Barcelona un coloso."},{"ns":"seg_1413","text":"Es el \"Oasis de los Mares\","},{"ns":"seg_1415","text":"la ciudad flotante más grande del mundo."},{"ns":"seg_1417","text":"Y hoy hemos subido a bordo."},{"ns":"seg_1419","text":"Ni una calle, ni un parque, ni un circo."},{"ns":"seg_1423","text":"Es un crucero, el más grande del mundo: 361 metros de largo."},{"ns":"seg_1427","text":"Como el Empire State, pero en horizontal y flotando."},{"ns":"seg_1430","text":"Esto no se puede explicar en palabras, la verdad."},{"ns":"seg_1433","text":"Estamos buscando el self-service y no lo encontramos."},{"ns":"seg_1435","text":"La verdad es que es una ciudad flotante."},{"ns":"seg_1437","text":"A bordo, 8500 personas."},{"ns":"seg_1439","text":"Hay un teatro con 2000 butacas, parque acuático, campo de golf,"},{"ns":"seg_1442","text":"y hasta un tiovivo."},{"ns":"seg_1445","text":"Centro de spa, muy a gustito, relajación."},{"ns":"seg_1448","text":"Lo del surf, lo de la gravedad esa que sube y te mantiene, la tirolina."},{"ns":"seg_1452","text":"Todo, todo lo que haya\""},{"ns":"seg_1453","text":"Hay más de 100 bares y restaurantes, para todos los gustos."},{"ns":"seg_1456","text":"Y de noche: teatros, discotecas, música en vivo, casinos, cines."},{"ns":"seg_1460","text":"Es una auténtica ciudad flotante que nunca duerme."},{"ns":"seg_1463","text":"Hace cuatro años que estaba esperando este momento."},{"ns":"seg_1466","text":"Y lo que pasa en este barco, como en Las Vegas, se queda aquí."},{"ns":"seg_1469","text":"Tiene 3000 camarotes, repartidos en 18 pisos."},{"ns":"seg_1478","text":"Se calcula alrededor de los 4 millones de euros"},{"ns":"seg_1480","text":"lo que va a aportar a la ciudad de Barcelona."},{"ns":"seg_1482","text":"Un crucero idéntico, \"Encanto de los Mares\","},{"ns":"seg_1485","text":"tendrá su puerto base en Barcelona a partir de 2015."},{"ns":"seg_1488","text":"Dice que, aunque lleva toda la vida estudiando el Universo,"},{"ns":"seg_1491","text":"aún no sabe por qué existe."},{"ns":"seg_1493","text":"Es lo que ha reconocido el físico Stephen Hawking,"},{"ns":"seg_1496","text":"que ha llegado hoy a Tenerife para participar en el Starmus,"},{"ns":"seg_1499","text":"el festival internacional que reunirá"},{"ns":"seg_1501","text":"a las principales autoridades en Astrofísica."},{"ns":"seg_1503","text":"Hawking intervendrá entre los días 22 y 27 de este mes"},{"ns":"seg_1506","text":"en unas jornadas en las que hablará del descubrimiento del Big Bang,"},{"ns":"seg_1509","text":"los efectos del bosón de Higgs y otros descubrimientos recientes."},{"ns":"seg_1516","text":"Protesta en Madrid contra el Toro de la Vega,"},{"ns":"seg_1519","text":"que se celebrará el próximo martes en Tordesillas, Valladolid."},{"ns":"seg_1522","text":"La manifestación, convocada por el Partido Animalista,"},{"ns":"seg_1525","text":"se ha iniciado con un acto simbólico"},{"ns":"seg_1530","text":"que ha consistido en romper unas 500 lanzas"},{"ns":"seg_1533","text":"adornadas con lazos negros y amarillos."},{"ns":"seg_1541","text":"El diestro Alejandro Talavante estará alejado de los ruedos"},{"ns":"seg_1544","text":"durante cuatro semanas por el percance sufrido ayer"},{"ns":"seg_1546","text":"en Baza, Granada."},{"ns":"seg_1548","text":"Al entrar a matar al sexto toro de la corrida"},{"ns":"seg_1550","text":"se cortó los tendones de la mano izquierda"},{"ns":"seg_1552","text":"con una banderilla."},{"ns":"seg_1554","text":"Esta mañana ha sido operado en Santander hasta donde viajó"},{"ns":"seg_1556","text":"para intentar cumplir su siguiente compromiso."},{"ns":"seg_1558","text":"Talavante asegura que intentará reaparecer en la feria de El Pilar."},{"ns":"seg_1574","text":"De blanco, con volantes o con tejidos vaporosos."},{"ns":"seg_1577","text":"Podrían ser perfectamente vestidos de novia."},{"ns":"seg_1580","text":"Son las propuestas de la diseñadora cordobesa Juana Martín."},{"ns":"seg_1585","text":"Una colección en la que las flores y la combinación blanco y negro"},{"ns":"seg_1588","text":"cobran fuerza."},{"ns":"seg_1590","text":"Después, la pasarela madrileña se ha llenado de color"},{"ns":"seg_1593","text":"con los diseños de Agatha Ruiz de la Prada."},{"ns":"seg_1595","text":"Para el día, algodón y lino,"},{"ns":"seg_1596","text":"satén, raso y organza para la noche."},{"ns":"seg_1632","text":"O te diferencias es muy difícil hacer que huequito."},{"ns":"seg_1644","text":"Cuida los patrones en diseños donde se mezcla lo más rompedor"},{"ns":"seg_1648","text":"con lo artesanal."},{"ns":"seg_1653","text":"Hoy Roberto Echevarría se sube a la pasarela de Madrid"},{"ns":"seg_1657","text":"después de haber convencido a la crítica de Nueva York."},{"ns":"seg_1662","text":"Fiel a su ideal de costura minuciosa y elegante"},{"ns":"seg_1667","text":"su estilo sofisticado y a la vez ágil y actual."},{"ns":"seg_1691","text":"Septiembre es mes de bodas."},{"ns":"seg_1693","text":"Según la Federación de Usuarios y Consumidores Independientes,"},{"ns":"seg_1696","text":"casarse en España cuesta de media unos 13.000 euros."},{"ns":"seg_1698","text":"Aunque 2013 fue relativamente malo para el sector,"},{"ns":"seg_1701","text":"este año los españoles no renuncian a casarse,"},{"ns":"seg_1703","text":"pero lo hacen con menos lujos."},{"ns":"seg_1706","text":"Acortar la lista de invitados"},{"ns":"seg_1708","text":"o prescindir de la tradicional barra libre es cada vez más habitual"},{"ns":"seg_1711","text":"entre los novios que quieren reducir su presupuesto."},{"ns":"seg_1714","text":"De los casi 13.000 euros que puede costar la factura,"},{"ns":"seg_1716","text":"más de la mitad se va en el banquete."},{"ns":"seg_1719","text":"Llevamos cuatro años sin subir el precio"},{"ns":"seg_1723","text":"y siempre tienes algún menú con precios más económicos."},{"ns":"seg_1728","text":"Aunque hay parejas que prefieren recortar en otras cosas."},{"ns":"seg_1731","text":"En los trajes, pues yendo a tiendas que tuvieran outlet y demás"},{"ns":"seg_1736","text":"y, luego, intentar hacer todo lo que hemos podido de nuestra mano."},{"ns":"seg_1743","text":"El secreto mejor guardado de la novia puede suponer"},{"ns":"seg_1746","text":"un ahorro de 1000 euros si es de otra temporada."},{"ns":"seg_1748","text":"Se pueden encontrar firmas de alta calidad, vestidos impecables,"},{"ns":"seg_1755","text":"simplemente que son una talla, un vestido,"},{"ns":"seg_1759","text":"pero son vestidos que llegan al 70% de descuento."},{"ns":"seg_1762","text":"Y a lo que tampoco renuncian es al viaje de novios."},{"ns":"seg_1766","text":"La filosofía es que se casan solo una vez"},{"ns":"seg_1768","text":"y que es el viaje de su vida."},{"ns":"seg_1772","text":"En lugar de hacer tres o cuatro semanas, están haciendo 15 días."},{"ns":"seg_1776","text":"Cada vez cuesta más darse el \"sí, quiero\","},{"ns":"seg_1779","text":"El año pasado se casaron 155.000 personas,"},{"ns":"seg_1782","text":"un 8% menos que el año anterior."},{"ns":"seg_1786","text":"Es uno de los últimos grandes festivales del verano."},{"ns":"seg_1789","text":"El DCode llega a su cuarta edición en Madrid"},{"ns":"seg_1791","text":"apostando por una sola jornada y con tres grandes escenarios."},{"ns":"seg_1795","text":"En uno de ellos está Eva Mora."},{"ns":"seg_1797","text":"Eva, se espera una larga noche con un menú musical muy variado."},{"ns":"seg_1807","text":"Es el único festival de música internacional"},{"ns":"seg_1812","text":"que se celebra en Madrid y que cuenta cada año con más de 5000"},{"ns":"seg_1816","text":"personas."},{"ns":"seg_1819","text":"Apuestan por la música británica y el sonido nacional independiente."},{"ns":"seg_1831","text":"Para los que no puedan venir lo pueden escuchar íntegramente"},{"ns":"seg_1835","text":"a través de radio tres en radio nacional de España."},{"ns":"seg_1867","text":"La mayoría viene atraída por el cartel."},{"ns":"seg_1884","text":"España es un lugar donde siempre hemos querido tocar."},{"ns":"seg_1904","text":"Siempre comparaciones con diferentes bandas"},{"ns":"seg_1907","text":"pero intentamos hacer lo que nos gusta."},{"ns":"seg_1912","text":"Volverán a España en noviembre."},{"ns":"seg_1918","text":"En Galicia tiene lugar este fin de semana"},{"ns":"seg_1920","text":"el Festival de la Luz que organiza la cantante Luz Casal."},{"ns":"seg_1923","text":"Se celebra en su pueblo natal, Boimorto"},{"ns":"seg_1925","text":"y quiere ser un homenaje al mundo agrario en decadencia."},{"ns":"seg_1941","text":"Síntesis entre festival y romería."},{"ns":"seg_1943","text":"Homenaje a un mundo agrario en retirada."},{"ns":"seg_1947","text":"Se venden productos del campo y los más pequeños conviven"},{"ns":"seg_1951","text":"con un entorno que ya no les ex próximo."},{"ns":"seg_1957","text":"Estamos encantados los niños con los animales."},{"ns":"seg_1960","text":"Se lo pasan bárbaro."},{"ns":"seg_1964","text":"El hecho de la vuelta a esta me parece una maravilla"},{"ns":"seg_1968","text":"y ver a las familias me emociona."},{"ns":"seg_1982","text":"Luz sola alumbra Este festival."},{"ns":"seg_1992","text":"1 festival benéfico en un espacio ganadero y agrícola"},{"ns":"seg_1997","text":"donde cabe todo tipo de música y de gente."},{"ns":"seg_2001","text":"Así transcurrió la tarde seguirá la noche."},{"ns":"seg_2005","text":"Tiempo ahora para el deporte."},{"ns":"seg_2006","text":"Como veíamos al comienzo del Telediario,"},{"ns":"seg_2008","text":"ya tenemos ganador de la Vuelta."},{"ns":"seg_2010","text":"No hay sorpresas y Alberto Contador"},{"ns":"seg_2012","text":"es el ganador virtual de la vuelta ciclista a españa."},{"ns":"seg_2014","text":"Hoy ha dejado sentenciada la carrera y de qué forma."},{"ns":"seg_2022","text":"Rl madrileño ha ganado la etapa"},{"ns":"seg_2024","text":"y le ha sacado 16 segundos en la linea de meta a Chris Froome."},{"ns":"seg_2026","text":"Mañana habrá dos españoles en en podio:"},{"ns":"seg_2028","text":"Contador primero y Valverde, tercero."},{"ns":"seg_2034","text":"El Barça seguirá lider una jornada mas."},{"ns":"seg_2036","text":"Hoy ha ganado al Athletic Club en el Camp Nou por 2 goles a 0,"},{"ns":"seg_2039","text":"doblete de Neymar."},{"ns":"seg_2040","text":"La conexion Messi-Neymar ha sido determinante:"},{"ns":"seg_2043","text":"dos pases de gol del argentino, dos goles del brasileño."},{"ns":"seg_2047","text":"Y todavia en juego en el Bernabeu el Real Madrid - Atletico de Madrid."},{"ns":"seg_2055","text":"Histórico."},{"ns":"seg_2056","text":"La Selección Española de Fútbol Femenino"},{"ns":"seg_2058","text":"jugará por primera en su historia un mundial."},{"ns":"seg_2061","text":"Será el año que viene, en canadá."},{"ns":"seg_2062","text":"España ha ganado en Rumanía, 0 a 2."},{"ns":"seg_2068","text":"El seleccionador español de baloncesto"},{"ns":"seg_2070","text":"no encuentra explicación a la derrota en cuartos de final"},{"ns":"seg_2073","text":"de la Copa del Mundo contra Francia."},{"ns":"seg_2075","text":"Orenga no piensa en dimitir."},{"ns":"seg_2102","text":"El ultimo km de Contador hoy ha sido de los que hacen historia."},{"ns":"seg_2105","text":"Y mañana ganará su tercera vuelta ciclista a españa."},{"ns":"seg_2108","text":"Marc ha ganado la penultima etapa con 16 segundos sobre Froome."},{"ns":"seg_2112","text":"Mañana el tramite de los 9 km de la crono indivudual."},{"ns":"seg_2118","text":"Que Froom esprintara para ganar dos segundos"},{"ns":"seg_2120","text":"en el último sprint intermedio"},{"ns":"seg_2122","text":"era solo un aperitivo de lo que esperaba."},{"ns":"seg_2125","text":"Y quedaba mucho Pan Do Zarco por delante,"},{"ns":"seg_2127","text":"esta novedosa subida a Ancares."},{"ns":"seg_2128","text":"Purito fue el primero en intentarlo a nueve kilómetros de meta."},{"ns":"seg_2131","text":"Apuesta a rojo ganador del catalán que consiguió abrir hueco."},{"ns":"seg_2134","text":"He probado desde lejos."},{"ns":"seg_2137","text":"Habrá gustos para todos."},{"ns":"seg_2138","text":"Me habré precipitado o no."},{"ns":"seg_2140","text":"Mil historias, pero al final lo hecho, hecho está."},{"ns":"seg_2142","text":"He disfrutado la subida, que es lo que vale."},{"ns":"seg_2144","text":"Contento de haber hecho el máximo."},{"ns":"seg_2146","text":"Y mientras Froome, empezó a derrochar vatios,"},{"ns":"seg_2148","text":"que terminaron con Valverde descolgado."},{"ns":"seg_2150","text":"No, yo tenía que poner mi ritmo."},{"ns":"seg_2152","text":"Bueno, al final yo, es que no sabes."},{"ns":"seg_2155","text":"Pero han estado diez segundos más"},{"ns":"seg_2157","text":"y luego han tenido que parar también."},{"ns":"seg_2159","text":"Luego ya me he dedicado a subir a mi marcha y ya está."},{"ns":"seg_2163","text":"Algo que le valió al final para alcanzar a Purito"},{"ns":"seg_2167","text":"y asegurar así,"},{"ns":"seg_2170","text":"su tercera plaza del podio."},{"ns":"seg_2172","text":"Los dos más fuertes iban por delante"},{"ns":"seg_2174","text":"Contador aguantando a rueda"},{"ns":"seg_2176","text":"los innumerables ataques de Froome."},{"ns":"seg_2180","text":"Pues quizá ocho o nueve veces."},{"ns":"seg_2182","text":"Y no cambios de ritmos pequeños sino cambios muy fuertes."},{"ns":"seg_2185","text":"Y después del enésimo ataque fue Alberto"},{"ns":"seg_2187","text":"quien sentenció la etapa y con ella,"},{"ns":"seg_2188","text":"la Vuelta Ciclista a España."},{"ns":"seg_2190","text":"Una jornada de ciclismo memorable y una foto"},{"ns":"seg_2192","text":"que nos ha dejado Alberto Contador"},{"ns":"seg_2194","text":"que nos recuerda aquella de la meta de Fuente De."},{"ns":"seg_2196","text":"La tercera Vuelta Ciclista a España del corredor de Pinto."},{"ns":"seg_2199","text":"Quería conseguir la Vuelta pero luego sí que es verdad"},{"ns":"seg_2201","text":"que se complicó todo y ya lo vi en algunos momentos imposible."},{"ns":"seg_2204","text":"Pero bueno poco a poco parece que fue mejorando la cosa."},{"ns":"seg_2206","text":"Me planté aquí pensando en una victoria de etapa"},{"ns":"seg_2209","text":"fue pasando los días y ahora estoy aquí,"},{"ns":"seg_2211","text":"y es que es un sueño."},{"ns":"seg_2223","text":"A mí nadie me ha regalado nada,"},{"ns":"seg_2230","text":"posiblemente lo que ha pensado contador antes de la llegada meta."},{"ns":"seg_2237","text":"El británico ha sido tal vez el mejor pero contador ha demostrado"},{"ns":"seg_2244","text":"que no perdone que quiere ser el auténtico ganador de la vuelta"},{"ns":"seg_2248","text":"ciclista."},{"ns":"seg_2269","text":"El Barça ha ganado por 2-0 al Athlétic Club de Bilbao"},{"ns":"seg_2271","text":"con doblete de Neymar."},{"ns":"seg_2273","text":"Los azulgrana son líderes con nueve puntos,"},{"ns":"seg_2275","text":"tres victorias en tres partidos."},{"ns":"seg_2277","text":"Los goles."},{"ns":"seg_2278","text":"1-0."},{"ns":"seg_2280","text":"Minuto 79, Neymar recibe una asistencia de Messi"},{"ns":"seg_2282","text":"y el brasileño bate a Gorka Iraizoz."},{"ns":"seg_2284","text":"La sociedad Messi-Neymar daba su primer fruto en ese partido."},{"ns":"seg_2296","text":"El balon al hueco de Messi y como remata Neymar"},{"ns":"seg_2298","text":"quien, por cierto, arrancó el partido en el banquillo."},{"ns":"seg_2301","text":"2-0."},{"ns":"seg_2305","text":"Messi inicia la carrera con el balon,"},{"ns":"seg_2307","text":"llega hasta el area pequeña, pase de la muerte a Neymar"},{"ns":"seg_2310","text":"y el brasileño define desde el punto de penalty."},{"ns":"seg_2312","text":"Han sido los dos primeros goles de neymar en esta Liga."},{"ns":"seg_2315","text":"Posible penalti de Mascherano a Aduriz."},{"ns":"seg_2317","text":"Min 25, patada de Aduriz a Mascherano."},{"ns":"seg_2319","text":"Min 30, Masch acabó la primera parte"},{"ns":"seg_2320","text":"pero sustituido por Piqué en el descanso."},{"ns":"seg_2323","text":"Posible penalti de Iraizoz sobre Munir."},{"ns":"seg_2328","text":"Le pitan falta a Munir."},{"ns":"seg_2337","text":"Min 33, posible penalti de Gurpegi sobre Munir."},{"ns":"seg_2343","text":"Min 39, golpe de Piqué sobre Muniain"},{"ns":"seg_2345","text":"Min 77, actuación de los porteros."},{"ns":"seg_2355","text":"Messi no sólo es el mejor del mundo no sólo por sus goles"},{"ns":"seg_2359","text":"sino por las asistencias que hace y si quisiera ser el mejor"},{"ns":"seg_2362","text":"defensor del mundo lo sería."},{"ns":"seg_2367","text":"Neymar Fueron dos jugadas de Leo, que para mí es el mejor del mundo,"},{"ns":"seg_2370","text":"un crack, y nuestro juego cada vez va a ser mejor."},{"ns":"seg_2374","text":"Cosas que le he visto hacer entrenando,"},{"ns":"seg_2376","text":"que no se la he visto a hacer ni a Oliver y Benji,"},{"ns":"seg_2378","text":"ni en la PlayStation."},{"ns":"seg_2394","text":"Tengo de todo como si fuera al supermercado."},{"ns":"seg_2395","text":"Están retomando la presión esa alta, que tan bien lo hacían antes."},{"ns":"seg_2404","text":"Finalmente, el Barça ha jugado con la tercera camiseta,"},{"ns":"seg_2406","text":"la de la senyera."},{"ns":"seg_2408","text":"Es la primera vez que lo hace en el Camp Nou."},{"ns":"seg_2410","text":"El Athlétic Club de Bilbao también ha jugado con la camiseta"},{"ns":"seg_2413","text":"que tiene los colores de la ikurriña."},{"ns":"seg_2422","text":"En estos momentos se sigue jugando el derby en el Bernabeu."},{"ns":"seg_2449","text":"Empate a cero en el partido del Málaga contra el Levante."},{"ns":"seg_2452","text":"El conjunto malagueño ha comenzado dominando el encuentro"},{"ns":"seg_2455","text":"pero sin aprovechar las numerosas ocasiones."},{"ns":"seg_2457","text":"En el minuto 61, Juanmi ha marcado un gol que ha sido anulado."},{"ns":"seg_2463","text":"El gran protagonista del partido"},{"ns":"seg_2464","text":"ha sido el guardamenta del equipo valenciano, Jesús Fernández."},{"ns":"seg_2471","text":"Y en el partido de anoche, Almería y Córdoba empataron a 1."},{"ns":"seg_2473","text":"Edgar adelantó al Almeria con este gol"},{"ns":"seg_2475","text":"en el minuto 12 de la primera parte."},{"ns":"seg_2477","text":"Fue a pase de Ximo Navarro."},{"ns":"seg_2479","text":"El Córdoba reacciono rápido y a los 7 minutos el argentino Fede"},{"ns":"seg_2482","text":"puso el 1 a 1 en el marcador."},{"ns":"seg_2486","text":"El Almeria reclamó penalty por mano de Campadabal"},{"ns":"seg_2490","text":"en el despeje de un remate de cabeza."},{"ns":"seg_2497","text":"La selección española fútbol femenino ha hecho historia."},{"ns":"seg_2501","text":"El año que viene jugará el mundial por primera vez en su historia."},{"ns":"seg_2508","text":"Y así lo han celebrado tras ganar en Rumanía por 0 goles a 2."},{"ns":"seg_2510","text":"Lo leemos en la cuenta de twitter de la Federación española de futbol."},{"ns":"seg_2516","text":"Natalia pablos ha sido la gran protagonista de la victoria."},{"ns":"seg_2518","text":"Natalia ha marcado los 2 goles de España."},{"ns":"seg_2521","text":"El primer gol llegó en el minuto 28 de la primera parte."},{"ns":"seg_2526","text":"Y el definitivo 0 a 2, a los 7 minutos de la segunda parte."},{"ns":"seg_2530","text":"España se clasifica para el mundial de manera brillante."},{"ns":"seg_2533","text":"Sólo ha cedido un empate."},{"ns":"seg_2534","text":"Todo lo demás, han sido victorias."},{"ns":"seg_2550","text":"Francia jugará la final de la Copa Davis."},{"ns":"seg_2554","text":"Ha ganado por 3 victorias a 0 a la República checa."},{"ns":"seg_2556","text":"Mientras Brasil y España empatan a 1 en la eliminatoria"},{"ns":"seg_2559","text":"por la permanencia en la Copa Davis"},{"ns":"seg_2561","text":"desde las 7 y media se está jugando el dobles en Sao Paulo."},{"ns":"seg_2564","text":"Y allí nos vamos, con nuestros compañeros que están retransmitiendo"},{"ns":"seg_2567","text":"el partido en teledeporte."},{"ns":"seg_2568","text":"Adelante nacho."},{"ns":"seg_2575","text":"Delicadas se han puesto las cosas en esta eliminatoria"},{"ns":"seg_2580","text":"por la permanencia en el grupo mundial de la Copa Davis."},{"ns":"seg_2590","text":"Estamos en el partido de dobles y las cosas no marchan bien."},{"ns":"seg_2604","text":"Brasil dominando el punto del doble."},{"ns":"seg_2607","text":"Estamos en el tercer set."},{"ns":"seg_2610","text":"Francia ha acabado tercera de la Copa del Mundo de Baloncesto."},{"ns":"seg_2615","text":"Esta tarde ha ganado a Lituania por 95 a 93."},{"ns":"seg_2618","text":"En España todavía le estamos dando vueltas"},{"ns":"seg_2620","text":"a la eliminación en cuartos."},{"ns":"seg_2623","text":"El seleccionador español no piensa en la dimisión."},{"ns":"seg_2638","text":"Yo tengo siempre ánimo,ilusión y ganas de trabajar."},{"ns":"seg_2641","text":"Apenas ha dormido en dos días,"},{"ns":"seg_2643","text":"ayer no se atrevió a ver la semifinal"},{"ns":"seg_2645","text":"y tampoco encuentra explicación a la derrota contra Francia."},{"ns":"seg_2648","text":"¿Le afectó a Marc su paternidad?"},{"ns":"seg_2655","text":"todavía me pregunto qué podemos hacer para cambiar el signo del"},{"ns":"seg_2659","text":"partido."},{"ns":"seg_2664","text":"Perdimos el ritmo."},{"ns":"seg_2677","text":"más vino con una ilusión tremenda y no salieran las cosas,"},{"ns":"seg_2681","text":"ni a él ni a nadie."},{"ns":"seg_2684","text":"Es el partido que más preparamos."},{"ns":"seg_2690","text":"Pero no salió ninguno de los planes."},{"ns":"seg_2697","text":"No hay minutos apenas si surge un imprevisto."},{"ns":"seg_2709","text":"Jorge Lorenzo saldrá mañana desde la pole"},{"ns":"seg_2712","text":"en el GP de San Marino."},{"ns":"seg_2713","text":"Ianone saldrá 2 y Valentino Rossi, 3 marc desde la segunda fila."},{"ns":"seg_2716","text":"Marc Márquez buscará su victoria numero 12 en 13 carreras."},{"ns":"seg_2721","text":"De ser asi en dos semanas podria ser campeon del mundo"},{"ns":"seg_2724","text":"de forma matematica."},{"ns":"seg_2735","text":"Jorge Lorenzo luchará por su primer triunfo en 2014."},{"ns":"seg_2736","text":"Márquez buscará mañana la victoria número 12 de 13 posibles."},{"ns":"seg_2740","text":"Hacía casi un año que el mallorquin no conseguía la pole."},{"ns":"seg_2744","text":"En moto2 Tito Rabat segundo y en moto3 primera fila para Rins"},{"ns":"seg_2747","text":"y Márquez."},{"ns":"seg_2749","text":"En fútbol playa, espectacular pase de chilena de España"},{"ns":"seg_2752","text":"que abría el marcador."},{"ns":"seg_2753","text":"La selección española ha empezado con ventaja de 2 goles ante Suiza,"},{"ns":"seg_2756","text":"pero finalmente ha perdido por 5 goles a 4."},{"ns":"seg_2758","text":"A pesar de la derrota,"},{"ns":"seg_2760","text":"España ya estaba clasificada para el mundial."},{"ns":"seg_2766","text":"Día de estreno en Teledeporte con la primera jornada de la liga"},{"ns":"seg_2769","text":"de fútbol sala."},{"ns":"seg_2770","text":"El Barcelona ha ganado por 2 goles a 6 al Levante."},{"ns":"seg_2772","text":"Sergio lozano abrió el marcador para los azulgranas,"},{"ns":"seg_2775","text":"que parten como favoritos esta temporada."},{"ns":"seg_2778","text":"La Liga la podrán ver cada sábado a La 1 en Teledeporte."},{"ns":"seg_2789","text":"Vamos cerrando la información deportiva."},{"ns":"seg_2802","text":"Vamos a conocer ahora la previsión del tiempo para los próximos días,"},{"ns":"seg_2805","text":"con José Miguel Gallardo."},{"ns":"seg_2821","text":"algunas tormentas del día de hoy ha sido más intensas."},{"ns":"seg_2838","text":"Desde el Meteosat observamos como la borrasca va enviando"},{"ns":"seg_2843","text":"esas bandas de nubosidad con bastante desarrollo vertical"},{"ns":"seg_2848","text":"y pueden traer tormentas importantes en algunas zonas."},{"ns":"seg_2859","text":"Hoy las ha valido en bastantes zonas y algunas bastante intensas."},{"ns":"seg_2867","text":"También hemos reflejado las tormentas sobre el Atlántico"},{"ns":"seg_2873","text":"porque toda esta masa de aire en las próximas horas y días"},{"ns":"seg_2877","text":"ir avanzando hacia la península."},{"ns":"seg_2882","text":"Aquí se refleja como las bandas de precipitación"},{"ns":"seg_2890","text":"afectarán al tercio occidental de la península."},{"ns":"seg_2898","text":"Reflejamos esta zona porque cuanto más próximas de la inestabilidad a"},{"ns":"seg_2902","text":"nosotros más fuertes serán esas tormentas."},{"ns":"seg_2908","text":"Aquí se generó una nueva perturbación"},{"ns":"seg_2913","text":"que seguirá aproximando al noroeste de la península"},{"ns":"seg_2917","text":"hacia el miércoles."},{"ns":"seg_2922","text":"A lo largo de estas próximas horas las nubes avanzarán a Galicia"},{"ns":"seg_2929","text":"y allí habrá tormentas que serán puntualmente fuertes."},{"ns":"seg_2940","text":"La situación para Galicia durante la tarde, con chubascos"},{"ns":"seg_2945","text":"y un viento residentes y ficando las costas del sureste."},{"ns":"seg_2949","text":"En Asturias,chubascos en casi todo el principado"},{"ns":"seg_2953","text":"con tormentas puntualmente fuertes."},{"ns":"seg_2961","text":"En Cantabria y País Vasco la tarde también se presenta inestable"},{"ns":"seg_2972","text":"en La Rioja algunos chubascos."},{"ns":"seg_2981","text":"Temperaturas máximas que en el valle del Ebro se acercan"},{"ns":"seg_2985","text":"a los 31°."},{"ns":"seg_3004","text":"Serán formando tormentas en la ibérica y en casi toda Cataluña."},{"ns":"seg_3008","text":"Temperaturas en torno a los 30 31 °."},{"ns":"seg_3018","text":"En la Comunidad Valenciana,nubes por la mañana que nos dejarán"},{"ns":"seg_3023","text":"tormentas y chubascos en buena parte de la provincia de Castellón."},{"ns":"seg_3037","text":"En las Islas Baleares algo de nubes en el norte."},{"ns":"seg_3043","text":"En Castilla y León el tiempo es más inestable en la mitad oeste"},{"ns":"seg_3048","text":"donde las tormentas serán más probables."},{"ns":"seg_3054","text":"No se descartan tormentas en zonas montañosas de Soria y Avila."},{"ns":"seg_3063","text":"Temperaturas de unos 28 o 29°."},{"ns":"seg_3065","text":"En Extremadura la tarde será también más inestable"},{"ns":"seg_3071","text":"con nubosidad que dejará tormentas al norte y al oeste."},{"ns":"seg_3080","text":"En Castilla la mancha nubes devolución."},{"ns":"seg_3085","text":"También algún chubasco en la comunidad de Madrid."},{"ns":"seg_3091","text":"En Andalucía el tiempo será tranquilo"},{"ns":"seg_3095","text":"con algunas nieblas durante la mañana."},{"ns":"seg_3100","text":"30 o 31°."},{"ns":"seg_3111","text":"En Canarias,el viento se puede soplar con fuerza"},{"ns":"seg_3114","text":"en algunas islas al norte."},{"ns":"seg_3117","text":"Volvemos a Almansa, a Albacete, para conocer la última hora"},{"ns":"seg_3120","text":"sobre la muerte del piloto de uno de los helicópteros"},{"ns":"seg_3122","text":"que trabajaban en un fuego declarado esta tarde."},{"ns":"seg_3125","text":"Araceli Sánchez, ¿qué más sabemos a esta hora?"},{"ns":"seg_3132","text":"Estamos pendientes de la llegada de la presidenta de Castilla La Mancha,"},{"ns":"seg_3137","text":"a la zona donde se producía este incidente."},{"ns":"seg_3142","text":"Varios vecinos anteriores ser evacuados por el fuego"},{"ns":"seg_3147","text":"y durante toda la noche los medios terrestres van a trabajar"},{"ns":"seg_3154","text":"y se prevé que durante la madrugada puede estar dominado el incendio."},{"ns":"seg_3159","text":"En total han participado en las labores de extinción"},{"ns":"seg_3167","text":"17 medios aéreos,51 terrestres y efectivos de las comunidades"},{"ns":"seg_3171","text":"de Castilla La Mancha y Murcia."},{"ns":"seg_3179","text":"Puede seguir todo lo relativo esta noticia en el canal 24 horas"},{"ns":"seg_3184","text":"y en esta página web."},{"ns":"seg_3186","text":"Las nuevas tecnologías fomentan nuevas formas de expresión"},{"ns":"seg_3189","text":"y a veces recuperan otras clásicas."},{"ns":"seg_3190","text":"Es el caso de la micropoesía,"},{"ns":"seg_3192","text":"que ha encontrado en las redes sociales"},{"ns":"seg_3194","text":"su mejor aliado para renacer."},{"ns":"seg_3196","text":"Para escribir un tuit hay que comprimir el mensaje"},{"ns":"seg_3198","text":"en 140 caracteres."},{"ns":"seg_3199","text":"Si el texto es una poesía, la labor se complica y eso se valora."},{"ns":"seg_3202","text":"Los micropoemas son un hashtag recurrente."},{"ns":"seg_3204","text":"Creo que les abre una puerta para entrar dentro de la poesía,"},{"ns":"seg_3207","text":"porque, a veces, entrar en los clásicos"},{"ns":"seg_3209","text":"en gente tan joven, cuesta."},{"ns":"seg_3212","text":"Creo que es una manera de que empiecen leyendo"},{"ns":"seg_3214","text":"y que acaben leyendo los clásicos."},{"ns":"seg_3216","text":"Ha vendido la mitad de la edición de su segundo libro en una semana."},{"ns":"seg_3219","text":"Lo que, nos cuentan desde su editorial,"},{"ns":"seg_3220","text":"es un éxito al tratarse de poesía."},{"ns":"seg_3222","text":"Sus escritos nacieron en un blog, luego se pasó a Twitter"},{"ns":"seg_3225","text":"para terminar publicando en papel."},{"ns":"seg_3231","text":"Muchas autoras de esta generación"},{"ns":"seg_3233","text":"empiezan escribiendo en las redes sociales;"},{"ns":"seg_3235","text":"no creo que las cosas sean excluyentes,"},{"ns":"seg_3240","text":"es decir, con respecto al libro físico."},{"ns":"seg_3242","text":"A pesar de la crisis que vive el sector,"},{"ns":"seg_3244","text":"los editores reconocen que ha surgido una nueva generación"},{"ns":"seg_3247","text":"de poetas, jóvenes lectores y pequeños editores."},{"ns":"seg_3250","text":"No sé si los jóvenes poetas están conectados con el rap,"},{"ns":"seg_3253","text":"el ritmo, la música, la canción, pero sí es cierto que han encontrado"},{"ns":"seg_3256","text":"en las llamadas redes sociales una forma clara de expresarse"},{"ns":"seg_3259","text":"y de llegar a un público, tal vez minoritario,"},{"ns":"seg_3262","text":"pero un público que, evidentemente, no existía."},{"ns":"seg_3265","text":"Un público ávido de nuevas experiencias,"},{"ns":"seg_3268","text":"que compra libros, abarrota salas donde se practica el aforismo"},{"ns":"seg_3272","text":"y que retuitea \"pequeños grandes poemas\"."},{"ns":"seg_3277","text":"Cada año los Premios Lux reconocen"},{"ns":"seg_3279","text":"a los mejores fotógrafos profesionales de nuestro país"},{"ns":"seg_3282","text":"en distintas categorías."},{"ns":"seg_3283","text":"Sus obras se pueden disfrutar en una exposición"},{"ns":"seg_3285","text":"que girará por toda España y que se acaba de inaugurar"},{"ns":"seg_3288","text":"en la sala EFTI de Madrid."},{"ns":"seg_3290","text":"Así nos despedimos hoy."},{"ns":"seg_3291","text":"Y después del Telediario, Informe Semanal."},{"ns":"seg_3293","text":"Hasta mañana."}]}